Workbook
Name NativeTimeline_InvoiceDate: #N/A
Name Slicer_Country: #N/A
Name Slicer_Month: #N/A

Sheet Dashboard
B2: Sales Performance Dashboard
F9: Total Revenue | J9: Total Orders | O9: Average Order Value
F11: =SUMPRODUCT(Clean_Data!D2:D100000,Clean_Data!F2:F100000) -> 23073.35 | J11: =COUNTA(Clean_Data!A2:A100000) -> 500 | O11: =SUMPRODUCT(Clean_Data!D2:D100000,Clean_Data!F2:F100000) -> 23073.35

Sheet Row_data
A1: InvoiceNo | B1: StockCode | C1: Description | D1: Quantity | E1: InvoiceDate | F1: UnitPrice | G1: CustomerID | H1: Country
A2: 50001 | B2: 84029G | C2: KNITTED UNION FLAG HOT WATER BOTTLE | D2: 8 | E2: 45304.528 | F2: 3.76 | G2: 12692 | H2: Portugal
A3: C50002 | B3: 84406B | C3: CREAM CUPID HEARTS COAT HANGER | D3: -1 | E3: 45594.633 | F3: 2.56 | G3: 12616 | H3: United Kingdom
A4: 50003 | B4: 82494L | C4: WOODEN FRAME ANTIQUE WHITE | D4: 14 | E4: 45393.721 | F4: 3.12 | G4: 12828 | H4: United Kingdom
A5: 50004 | B5: 22720 | C5: SET OF 3 CAKE TINS PANTRY DESIGN | D5: 11 | E5: 45649.633 | F5: 4.58 | G5: 12781 | H5: Netherlands
A6: 50005 | B6: 84029G | C6: KNITTED UNION FLAG HOT WATER BOTTLE | D6: 4 | E6: 45339.603 | F6: 3.29 | G6: 12270 | H6: United Kingdom
A7: 50006 | B7: 20725 | C7: LUNCH BAG RED RETROSPOT | D7: 13 | E7: 45566.422 | F7: 1.57 | G7: 12643 | H7: Australia
A8: 50007 | B8: 21212 | C8: PACK OF 72 RETROSPOT CAKE CASES | D8: 23 | E8: 45587.469 | F8: 0.59 | G8: 12791 | H8: Spain
A9: 50008 | B9: 84406B | C9: CREAM CUPID HEARTS COAT HANGER | D9: 13 | E9: 45411.405 | F9: 2.95 | G9: 12373 | H9: France
A10: 50009 | B10: 21212 | C10: PACK OF 72 RETROSPOT CAKE CASES | D10: 22 | E10: 45473.482 | F10: 0.65 | G10: 12663 | H10: Germany
A11: 50010 | B11: 84991 | C11: 60 TEATIME FAIRY CAKE CASES | D11: 18 | E11: 45617.455 | F11: 0.5 | G11: 12388 | H11: Spain
A12: 50011 | B12: 82494L | C12: WOODEN FRAME ANTIQUE WHITE | D12: 2 | E12: 45404.564 | F12: 2.54 | G12: 12323 | H12: Belgium
A13: 50012 | B13: 47566 | C13: PARTY BUNTING | D13: 19 | E13: 45325.483 | F13: 4.75 | G13: 12671 | H13: Switzerland
A14: 50013 | B14: 22386 | C14: JUMBO BAG PINK POLKADOT | D14: 5 | E14: 45621.659 | F14: 1.83 | G14: 12574 | H14: Portugal
A15: 50014 | B15: 47566 | C15: PARTY BUNTING | D15: 19 | E15: 45591.637 | F15: 4.59 | G15: 12141 | H15: Portugal
A16: 50015 | B16: 23203 | C16: JUMBO BAG DOILEY PATTERNS | D16: 4 | E16: 45338.367 | F16: 1.88 | G16: 12696 | H16: Belgium
A17: 50016 | B17: 84991 | C17: 60 TEATIME FAIRY CAKE CASES | D17: 13 | E17: 45324.607 | F17: 0.56 | G17: 12257 | H17: Portugal
A18: 50017 | B18: 85123A | C18: WHITE HANGING HEART T-LIGHT HOLDER | D18: 22 | E18: 45640.415 | F18: 2.84 | G18: 12787 | H18: Netherlands
A19: 50018 | B19: 84029G | C19: KNITTED UNION FLAG HOT WATER BOTTLE | D19: 6 | E19: 45442.642 | F19: 4.01 | H19: Spain
A20: 50019 | B20: POST | C20: POSTAGE | D20: 4 | E20: 45383.694 | F20: 17.18 | G20: 12654 | H20: Portugal
A21: 50020 | B21: 84991 | C21: 60 TEATIME FAIRY CAKE CASES | D21: 12 | E21: 45393.442 | F21: 0.57 | G21: 12797 | H21: Portugal
A22: C50021 | B22: 85123A | C22: WHITE HANGING HEART T-LIGHT HOLDER | D22: -6 | E22: 45598.563 | F22: 2.95 | G22: 12851 | H22: Spain
A23: 50022 | B23: 22423 | C23: REGENCY CAKESTAND 3 TIER | D23: 19 | E23: 45321.504 | F23: 11.22 | G23: 12497 | H23: Germany
A24: 50023 | B24: 82494L | C24: WOODEN FRAME ANTIQUE WHITE | D24: 22 | E24: 45356.424 | F24: 3.08 | G24: 12271 | H24: Portugal
A25: 50024 | B25: 84991 | C25: 60 TEATIME FAIRY CAKE CASES | D25: 18 | E25: 45508.483 | F25: 0.6 | G25: 12730 | H25: Spain
A26: 50025 | B26: 22386 | C26: JUMBO BAG PINK POLKADOT | D26: 15 | E26: 45635.599 | F26: 1.97 | G26: 12253 | H26: EIRE
A27: 50026 | B27: 84406B | C27: CREAM CUPID HEARTS COAT HANGER | D27: 19 | E27: 45465.348 | F27: 2.9 | G27: 12007 | H27: Germany
A28: 50027 | B28: 71053 | C28: WHITE METAL LANTERN | D28: 2 | E28: 45409.381 | F28: 2.97 | G28: 12243 | H28: Spain
A29: 50028 | B29: 23203 | C29: JUMBO BAG DOILEY PATTERNS | D29: 5 | E29: 45401.717 | F29: 2.41 | G29: 12590 | H29: Switzerland
A30: 50029 | B30: 22423 | C30: REGENCY CAKESTAND 3 TIER | D30: 7 | E30: 45534.622 | F30: 13.78 | G30: 12362 | H30: Belgium
A31: 50030 | B31: 85099B | C31: JUMBO BAG RED RETROSPOT | D31: 22 | E31: 45531.372 | F31: 2.24 | G31: 12062 | H31: Belgium
A32: 50031 | B32: 22086 | C32: PAPER CHAIN KIT 50'S CHRISTMAS | D32: 7 | E32: 45347.51 | F32: 2.97 | G32: 12432 | H32: France
A33: 50032 | B33: 47566 | C33: PARTY BUNTING | D33: 3 | E33: 45528.51 | F33: 5.7 | G33: 12563 | H33: Germany
A34: 50033 | B34: 71053 | C34: WHITE METAL LANTERN | D34: 1 | E34: 45625.717 | F34: 3.98 | G34: 12869 | H34: EIRE
A35: 50034 | B35: 22720 | C35: SET OF 3 CAKE TINS PANTRY DESIGN | D35: 16 | E35: 45500.678 | F35: 4.9 | G35: 12060 | H35: France
A36: 50035 | B36: 22386 | C36: JUMBO BAG PINK POLKADOT | D36: 9 | E36: 45293.61 | F36: 2.19 | G36: 12292 | H36: Belgium
A37: 50036 | B37: 82494L | C37: WOODEN FRAME ANTIQUE WHITE | D37: 5 | E37: 45630.679 | F37: 2.73 | G37: 12059 | H37: Australia
A38: C50037 | B38: 82494L | C38: WOODEN FRAME ANTIQUE WHITE | D38: -2 | E38: 45323.556 | F38: 3.03 | G38: 12873 | H38: Portugal
A39: 50038 | B39: 22720 | C39: SET OF 3 CAKE TINS PANTRY DESIGN | D39: 3 | E39: 45321.694 | F39: 4.33 | G39: 12069 | H39: EIRE
A40: 50039 | B40: 22386 | C40: JUMBO BAG PINK POLKADOT | D40: 8 | E40: 45353.738 | F40: 1.68 | G40: 12083 | H40: Belgium
A41: 50040 | B41: 84970S | C41: HANGING HEART ZINC T-LIGHT HOLDER | D41: 11 | E41: 45581.705 | F41: 1.15 | G41: 12733 | H41: Netherlands
A42: 50041 | B42: 22423 | C42: REGENCY CAKESTAND 3 TIER | D42: 5 | E42: 45427.615 | F42: 12.18 | G42: 12323 | H42: Germany
A43: 50042 | B43: 85123A | C43: WHITE HANGING HEART T-LIGHT HOLDER | D43: 4 | E43: 45526.733 | F43: 2.36 | G43: 12271 | H43: France
A44: 50043 | B44: 21212 | C44: PACK OF 72 RETROSPOT CAKE CASES | D44: 12 | E44: 45327.507 | F44: 0.55 | G44: 12556 | H44: Spain
A45: 50044 | B45: 84991 | C45: 60 TEATIME FAIRY CAKE CASES | D45: 1 | E45: 45626.709 | F45: 0.57 | G45: 12954 | H45: Germany
A46: 50045 | B46: 84879 | C46: ASSORTED COLOUR BIRD ORNAMENT | D46: 4 | E46: 45427.415 | F46: 1.53 | G46: 12288 | H46: Australia
A47: 50046 | B47: 22727 | C47: ALARM CLOCK BAKELIKE RED | D47: 22 | E47: 45467.478 | F47: 3.53 | G47: 12500 | H47: Spain
A48: C50047 | B48: 71053 | C48: WHITE METAL LANTERN | D48: -6 | E48: 45339.634 | F48: 3.8 | G48: 12652 | H48: Spain
A49: 50048 | B49: 22720 | C49: SET OF 3 CAKE TINS PANTRY DESIGN | D49: 23 | E49: 45518.725 | F49: 4.22 | G49: 12077 | H49: France
A50: 50049 | B50: 82494L | C50: WOODEN FRAME ANTIQUE WHITE | D50: 19 | E50: 45310.596 | F50: 2.95 | G50: 12042 | H50: Spain
A51: 50050 | B51: 21212 | C51: PACK OF 72 RETROSPOT CAKE CASES | D51: 7 | E51: 45312.588 | F51: 0.6 | G51: 12362 | H51: Portugal
A52: 50051 | B52: 85099B | C52: JUMBO BAG RED RETROSPOT | D52: 8 | E52: 45609.443 | F52: 2.48 | G52: 12830 | H52: France
A53: 50052 | B53: 85099B | C53: JUMBO BAG RED RETROSPOT | D53: 24 | E53: 45304.46 | F53: 2.34 | G53: 12421 | H53: EIRE
A54: 50053 | B54: 47566 | C54: PARTY BUNTING | D54: 13 | E54: 45373.41 | F54: 5.7 | G54: 12227 | H54: EIRE
A55: 50054 | B55: 20725 | C55: LUNCH BAG RED RETROSPOT | D55: 8 | E55: 45471.55 | F55: 1.78 | G55: 12408 | H55: Netherlands
A56: 50055 | B56: 47566 | C56: PARTY BUNTING | D56: 12 | E56: 45327.531 | F56: 4.9 | G56: 12863 | H56: Portugal
A57: 50056 | B57: 22086 | C57: PAPER CHAIN KIT 50'S CHRISTMAS | D57: 9 | E57: 45306.415 | F57: 3.5 | G57: 12271 | H57: United Kingdom
A58: 50057 | B58: 84029G | C58: KNITTED UNION FLAG HOT WATER BOTTLE | D58: 12 | E58: 45597.642 | F58: 3.25 | G58: 12620 | H58: Portugal
A59: 50058 | B59: 84029G | C59: KNITTED UNION FLAG HOT WATER BOTTLE | D59: 7 | E59: 45489.743 | F59: 3.72 | G59: 12001 | H59: Portugal
A60: 50059 | B60: 82494L | C60: WOODEN FRAME ANTIQUE WHITE | D60: 12 | E60: 45643.473 | F60: 3.49 | G60: 12942 | H60: Netherlands
A61: 50060 | B61: 84991 | C61: 60 TEATIME FAIRY CAKE CASES | D61: 24 | E61: 45452.422 | F61: 0.57 | G61: 12682 | H61: Belgium
A62: 50061 | B62: 22086 | C62: PAPER CHAIN KIT 50'S CHRISTMAS | D62: 18 | E62: 45498.543 | F62: 2.94 | G62: 12962 | H62: Belgium
A63: 50062 | B63: 22720 | C63: SET OF 3 CAKE TINS PANTRY DESIGN | D63: 10 | E63: 45607.738 | F63: 5.65 | G63: 12311 | H63: Spain
A64: 50063 | B64: 22727 | C64: ALARM CLOCK BAKELIKE RED | D64: 20 | E64: 45512.745 | F64: 3.8 | G64: 12452 | H64: EIRE
A65: 50064 | B65: POST | C65: POSTAGE | D65: 22 | E65: 45534.453 | F65: 18.55 | G65: 12648 | H65: Australia
A66: 50065 | B66: 22086 | C66: PAPER CHAIN KIT 50'S CHRISTMAS | D66: 22 | E66: 45339.5 | F66: 3.34 | G66: 12150 | H66: United Kingdom
A67: 50066 | B67: 71053 | C67: WHITE METAL LANTERN | D67: 20 | E67: 45417.671 | F67: 2.97 | G67: 12424 | H67: Australia
A68: 50067 | B68: 22727 | C68: ALARM CLOCK BAKELIKE RED | D68: 16 | E68: 45648.606 | F68: 3.38 | G68: 12704 | H68: United Kingdom
A69: 50068 | B69: 84029G | C69: KNITTED UNION FLAG HOT WATER BOTTLE | D69: 6 | E69: 45509.489 | F69: 3.71 | G69: 12475 | H69: United Kingdom
A70: 50069 | B70: 82494L | C70: WOODEN FRAME ANTIQUE WHITE | D70: 15 | E70: 45419.419 | F70: 2.99 | G70: 12543 | H70: Portugal
A71: 50070 | B71: 84991 | C71: 60 TEATIME FAIRY CAKE CASES | D71: 20 | E71: 45454.648 | F71: 0.64 | G71: 12436 | H71: Portugal
A72: 50071 | B72: 20725 | C72: LUNCH BAG RED RETROSPOT | D72: 15 | E72: 45373.671 | F72: 1.55 | G72: 12652 | H72: Spain
A73: 50072 | B73: POST | C73: POSTAGE | E73: 45540.503 | F73: 19.8 | G73: 12240 | H73: Spain
A74: 50073 | B74: 22086 | C74: PAPER CHAIN KIT 50'S CHRISTMAS | D74: 3 | E74: 45455.717 | F74: 2.75 | G74: 12710 | H74: France
A75: 50074 | B75: 22727 | C75: ALARM CLOCK BAKELIKE RED | D75: 14 | E75: 45324.628 | F75: 3.8 | G75: 12063 | H75: EIRE
A76: C50075 | B76: 85099B | C76: JUMBO BAG RED RETROSPOT | D76: -7 | E76: 45491.749 | F76: 2.12 | G76: 12965 | H76: Netherlands
A77: 50076 | B77: 22960 | C77: JAM MAKING SET WITH JARS | D77: 18 | E77: 45491.631 | F77: 4.42 | G77: 12617 | H77: EIRE
A78: 50077 | B78: 23203 | C78: JUMBO BAG DOILEY PATTERNS | D78: 14 | E78: 45404.527 | F78: 2.05 | G78: 12684 | H78: Belgium
A79: 50078 | B79: 22720 | C79: SET OF 3 CAKE TINS PANTRY DESIGN | D79: 20 | E79: 45531.424 | F79: 5.78 | G79: 12606 | H79: Australia
A80: 50079 | B80: 85123A | C80: WHITE HANGING HEART T-LIGHT HOLDER | D80: 5 | E80: 45334.637 | F80: 2.33 | G80: 12266 | H80: Belgium
A81: 50080 | B81: 22086 | C81: PAPER CHAIN KIT 50'S CHRISTMAS | D81: 11 | E81: 45400.656 | F81: 3.42 | G81: 12284 | H81: Belgium
A82: 50081 | B82: 47566 | C82: PARTY BUNTING | D82: 1 | E82: 45333.667 | F82: 4.3 | G82: 12974 | H82: Netherlands
A83: C50082 | B83: 22423 | C83: REGENCY CAKESTAND 3 TIER | D83: -1 | E83: 45624.382 | F83: 15.08 | G83: 12204 | H83: United Kingdom
A84: 50083 | B84: 84991 | C84: 60 TEATIME FAIRY CAKE CASES | D84: 5 | E84: 45370.503 | F84: 0.49 | G84: 12970 | H84: EIRE
A85: 50084 | B85: 20725 | C85: LUNCH BAG RED RETROSPOT | D85: 12 | E85: 45650.515 | F85: 1.75 | G85: 12765 | H85: Germany
A86: C50085 | B86: 22720 | C86: SET OF 3 CAKE TINS PANTRY DESIGN | D86: -5 | E86: 45451.41 | F86: 5.21 | G86: 12929 | H86: Belgium
A87: 50086 | B87: 22386 | C87: JUMBO BAG PINK POLKADOT | D87: 19 | E87: 45393.387 | F87: 2.09 | G87: 12104 | H87: Spain
A88: 50087 | B88: 84991 | C88: 60 TEATIME FAIRY CAKE CASES | D88: 2 | E88: 45353.735 | F88: 0.55 | G88: 12379 | H88: Germany
A89: 50088 | B89: POST | C89: POSTAGE | D89: 1 | E89: 45623.576 | F89: 20.48 | G89: 12108 | H89: Belgium
A90: 50089 | B90: 21212 | C90: PACK OF 72 RETROSPOT CAKE CASES | D90: 23 | E90: 45617.66 | F90: 0.5 | G90: 12534 | H90: Spain
A91: 50090 | B91: 84991 | C91: 60 TEATIME FAIRY CAKE CASES | D91: 15 | E91: 45567.677 | F91: 0.61 | G91: 12274 | H91: Netherlands
A92: 50091 | B92: 22423 | C92: REGENCY CAKESTAND 3 TIER | D92: 15 | E92: 45336.531 | F92: 12.91 | G92: 12624 | H92: Belgium
A93: 50092 | B93: 22086 | C93: PAPER CHAIN KIT 50'S CHRISTMAS | D93: 11 | E93: 45306.685 | F93: 2.73 | G93: 12816 | H93: Spain
A94: C50093 | B94: 22086 | C94: PAPER CHAIN KIT 50'S CHRISTMAS | D94: -4 | E94: 45435.529 | F94: 2.6 | G94: 12737 | H94: Belgium
A95: 50094 | B95: 23203 | C95: JUMBO BAG DOILEY PATTERNS | D95: 23 | E95: 45576.504 | F95: 2.29 | G95: 12458 | H95: United Kingdom
A96: 50095 | B96: 84406B | C96: CREAM CUPID HEARTS COAT HANGER | D96: 13 | E96: 45442.49 | F96: 2.63 | G96: 12595 | H96: Netherlands
A97: 50096 | B97: 23203 | C97: JUMBO BAG DOILEY PATTERNS | D97: 12 | E97: 45575.71 | F97: 2.31 | G97: 12338 | H97: Netherlands
A98: 50097 | B98: 20725 | C98: LUNCH BAG RED RETROSPOT | D98: 9 | E98: 45430.551 | F98: 1.82 | G98: 12323 | H98: Germany
A99: 50098 | B99: 82494L | C99: WOODEN FRAME ANTIQUE WHITE | D99: 7 | E99: 45645.465 | F99: 3.01 | G99: 12741 | H99: Australia
A100: 50099 | B100: POST | C100: POSTAGE | D100: 4 | E100: 45597.534 | F100: 17.17 | G100: 12369 | H100: France
...

Sheet Clean_Data
A1: InvoiceNo | B1: StockCode | C1: Description | D1: Quantity | E1: InvoiceDate | F1: UnitPrice | G1: CustomerID | H1: Country | I1: Revenue | J1: Month | K1: Year | L1: OrderStatus | M1: CustomerSegment
A2: 50001 | B2: 84029G | C2: KNITTED UNION FLAG HOT WATER BOTTLE | D2: 8 | E2: 45304.528 | F2: 3.76 | G2: 12692 | H2: Portugal | I2: =D2*F2 -> 30.08 | J2: =TEXT(E2,"mmm") -> Jan | K2: =YEAR(E2) -> 2024 | L2: =IF(OR(LEFT(A2,1)="C",D2<0),"Cancelled","Completed") -> Completed | M2: =IF(G2=0,"Unknown",IF(MOD(G2,3)=0,"Wholesale",IF(MOD(G2,2)=0,"Returning","New"))) -> Returning
A3: C50002 | B3: 84406B | C3: CREAM CUPID HEARTS COAT HANGER | D3: -1 | E3: 45594.633 | F3: 2.56 | G3: 12616 | H3: United Kingdom | I3: =D3*F3 -> -2.56 | J3: =TEXT(E3,"mmm") -> Oct | K3: =YEAR(E3) -> 2024 | L3: =IF(OR(LEFT(A3,1)="C",D3<0),"Cancelled","Completed") -> Cancelled | M3: =IF(G3=0,"Unknown",IF(MOD(G3,3)=0,"Wholesale",IF(MOD(G3,2)=0,"Returning","New"))) -> Returning
A4: 50003 | B4: 82494L | C4: WOODEN FRAME ANTIQUE WHITE | D4: 14 | E4: 45393.721 | F4: 3.12 | G4: 12828 | H4: United Kingdom | I4: =D4*F4 -> 43.68 | J4: =TEXT(E4,"mmm") -> Apr | K4: =YEAR(E4) -> 2024 | L4: =IF(OR(LEFT(A4,1)="C",D4<0),"Cancelled","Completed") -> Completed | M4: =IF(G4=0,"Unknown",IF(MOD(G4,3)=0,"Wholesale",IF(MOD(G4,2)=0,"Returning","New"))) -> Wholesale
A5: 50004 | B5: 22720 | C5: SET OF 3 CAKE TINS PANTRY DESIGN | D5: 11 | E5: 45649.633 | F5: 4.58 | G5: 12781 | H5: Netherlands | I5: =D5*F5 -> 50.38 | J5: =TEXT(E5,"mmm") -> Dec | K5: =YEAR(E5) -> 2024 | L5: =IF(OR(LEFT(A5,1)="C",D5<0),"Cancelled","Completed") -> Completed | M5: =IF(G5=0,"Unknown",IF(MOD(G5,3)=0,"Wholesale",IF(MOD(G5,2)=0,"Returning","New"))) -> New
A6: 50005 | B6: 84029G | C6: KNITTED UNION FLAG HOT WATER BOTTLE | D6: 4 | E6: 45339.603 | F6: 3.29 | G6: 12270 | H6: United Kingdom | I6: =D6*F6 -> 13.16 | J6: =TEXT(E6,"mmm") -> Feb | K6: =YEAR(E6) -> 2024 | L6: =IF(OR(LEFT(A6,1)="C",D6<0),"Cancelled","Completed") -> Completed | M6: =IF(G6=0,"Unknown",IF(MOD(G6,3)=0,"Wholesale",IF(MOD(G6,2)=0,"Returning","New"))) -> Wholesale
A7: 50006 | B7: 20725 | C7: LUNCH BAG RED RETROSPOT | D7: 13 | E7: 45566.422 | F7: 1.57 | G7: 12643 | H7: Australia | I7: =D7*F7 -> 20.41 | J7: =TEXT(E7,"mmm") -> Oct | K7: =YEAR(E7) -> 2024 | L7: =IF(OR(LEFT(A7,1)="C",D7<0),"Cancelled","Completed") -> Completed | M7: =IF(G7=0,"Unknown",IF(MOD(G7,3)=0,"Wholesale",IF(MOD(G7,2)=0,"Returning","New"))) -> New
A8: 50007 | B8: 21212 | C8: PACK OF 72 RETROSPOT CAKE CASES | D8: 23 | E8: 45587.469 | F8: 0.59 | G8: 12791 | H8: Spain | I8: =D8*F8 -> 13.57 | J8: =TEXT(E8,"mmm") -> Oct | K8: =YEAR(E8) -> 2024 | L8: =IF(OR(LEFT(A8,1)="C",D8<0),"Cancelled","Completed") -> Completed | M8: =IF(G8=0,"Unknown",IF(MOD(G8,3)=0,"Wholesale",IF(MOD(G8,2)=0,"Returning","New"))) -> New
A9: 50008 | B9: 84406B | C9: CREAM CUPID HEARTS COAT HANGER | D9: 13 | E9: 45411.405 | F9: 2.95 | G9: 12373 | H9: France | I9: =D9*F9 -> 38.35 | J9: =TEXT(E9,"mmm") -> Apr | K9: =YEAR(E9) -> 2024 | L9: =IF(OR(LEFT(A9,1)="C",D9<0),"Cancelled","Completed") -> Completed | M9: =IF(G9=0,"Unknown",IF(MOD(G9,3)=0,"Wholesale",IF(MOD(G9,2)=0,"Returning","New"))) -> New
A10: 50009 | B10: 21212 | C10: PACK OF 72 RETROSPOT CAKE CASES | D10: 22 | E10: 45473.482 | F10: 0.65 | G10: 12663 | H10: Germany | I10: =D10*F10 -> 14.3 | J10: =TEXT(E10,"mmm") -> Jun | K10: =YEAR(E10) -> 2024 | L10: =IF(OR(LEFT(A10,1)="C",D10<0),"Cancelled","Completed") -> Completed | M10: =IF(G10=0,"Unknown",IF(MOD(G10,3)=0,"Wholesale",IF(MOD(G10,2)=0,"Returning","New"))) -> Wholesale
A11: 50010 | B11: 84991 | C11: 60 TEATIME FAIRY CAKE CASES | D11: 18 | E11: 45617.455 | F11: 0.5 | G11: 12388 | H11: Spain | I11: =D11*F11 -> 9 | J11: =TEXT(E11,"mmm") -> Nov | K11: =YEAR(E11) -> 2024 | L11: =IF(OR(LEFT(A11,1)="C",D11<0),"Cancelled","Completed") -> Completed | M11: =IF(G11=0,"Unknown",IF(MOD(G11,3)=0,"Wholesale",IF(MOD(G11,2)=0,"Returning","New"))) -> Returning
A12: 50011 | B12: 82494L | C12: WOODEN FRAME ANTIQUE WHITE | D12: 2 | E12: 45404.564 | F12: 2.54 | G12: 12323 | H12: Belgium | I12: =D12*F12 -> 5.08 | J12: =TEXT(E12,"mmm") -> Apr | K12: =YEAR(E12) -> 2024 | L12: =IF(OR(LEFT(A12,1)="C",D12<0),"Cancelled","Completed") -> Completed | M12: =IF(G12=0,"Unknown",IF(MOD(G12,3)=0,"Wholesale",IF(MOD(G12,2)=0,"Returning","New"))) -> New
A13: 50012 | B13: 47566 | C13: PARTY BUNTING | D13: 19 | E13: 45325.483 | F13: 4.75 | G13: 12671 | H13: Switzerland | I13: =D13*F13 -> 90.25 | J13: =TEXT(E13,"mmm") -> Feb | K13: =YEAR(E13) -> 2024 | L13: =IF(OR(LEFT(A13,1)="C",D13<0),"Cancelled","Completed") -> Completed | M13: =IF(G13=0,"Unknown",IF(MOD(G13,3)=0,"Wholesale",IF(MOD(G13,2)=0,"Returning","New"))) -> New
A14: 50013 | B14: 22386 | C14: JUMBO BAG PINK POLKADOT | D14: 5 | E14: 45621.659 | F14: 1.83 | G14: 12574 | H14: Portugal | I14: =D14*F14 -> 9.15 | J14: =TEXT(E14,"mmm") -> Nov | K14: =YEAR(E14) -> 2024 | L14: =IF(OR(LEFT(A14,1)="C",D14<0),"Cancelled","Completed") -> Completed | M14: =IF(G14=0,"Unknown",IF(MOD(G14,3)=0,"Wholesale",IF(MOD(G14,2)=0,"Returning","New"))) -> Returning
A15: 50014 | B15: 47566 | C15: PARTY BUNTING | D15: 19 | E15: 45591.637 | F15: 4.59 | G15: 12141 | H15: Portugal | I15: =D15*F15 -> 87.21 | J15: =TEXT(E15,"mmm") -> Oct | K15: =YEAR(E15) -> 2024 | L15: =IF(OR(LEFT(A15,1)="C",D15<0),"Cancelled","Completed") -> Completed | M15: =IF(G15=0,"Unknown",IF(MOD(G15,3)=0,"Wholesale",IF(MOD(G15,2)=0,"Returning","New"))) -> Wholesale
A16: 50015 | B16: 23203 | C16: JUMBO BAG DOILEY PATTERNS | D16: 4 | E16: 45338.367 | F16: 1.88 | G16: 12696 | H16: Belgium | I16: =D16*F16 -> 7.52 | J16: =TEXT(E16,"mmm") -> Feb | K16: =YEAR(E16) -> 2024 | L16: =IF(OR(LEFT(A16,1)="C",D16<0),"Cancelled","Completed") -> Completed | M16: =IF(G16=0,"Unknown",IF(MOD(G16,3)=0,"Wholesale",IF(MOD(G16,2)=0,"Returning","New"))) -> Wholesale
A17: 50016 | B17: 84991 | C17: 60 TEATIME FAIRY CAKE CASES | D17: 13 | E17: 45324.607 | F17: 0.56 | G17: 12257 | H17: Portugal | I17: =D17*F17 -> 7.28 | J17: =TEXT(E17,"mmm") -> Feb | K17: =YEAR(E17) -> 2024 | L17: =IF(OR(LEFT(A17,1)="C",D17<0),"Cancelled","Completed") -> Completed | M17: =IF(G17=0,"Unknown",IF(MOD(G17,3)=0,"Wholesale",IF(MOD(G17,2)=0,"Returning","New"))) -> New
A18: 50017 | B18: 85123A | C18: WHITE HANGING HEART T-LIGHT HOLDER | D18: 22 | E18: 45640.415 | F18: 2.84 | G18: 12787 | H18: Netherlands | I18: =D18*F18 -> 62.48 | J18: =TEXT(E18,"mmm") -> Dec | K18: =YEAR(E18) -> 2024 | L18: =IF(OR(LEFT(A18,1)="C",D18<0),"Cancelled","Completed") -> Completed | M18: =IF(G18=0,"Unknown",IF(MOD(G18,3)=0,"Wholesale",IF(MOD(G18,2)=0,"Returning","New"))) -> New
A19: 50018 | B19: 84029G | C19: KNITTED UNION FLAG HOT WATER BOTTLE | D19: 6 | E19: 45442.642 | F19: 4.01 | G19: 0 | H19: Spain | I19: =D19*F19 -> 24.06 | J19: =TEXT(E19,"mmm") -> May | K19: =YEAR(E19) -> 2024 | L19: =IF(OR(LEFT(A19,1)="C",D19<0),"Cancelled","Completed") -> Completed | M19: =IF(G19=0,"Unknown",IF(MOD(G19,3)=0,"Wholesale",IF(MOD(G19,2)=0,"Returning","New"))) -> Unknown
A20: 50019 | B20: POST | C20: POSTAGE | D20: 4 | E20: 45383.694 | F20: 17.18 | G20: 12654 | H20: Portugal | I20: =D20*F20 -> 68.72 | J20: =TEXT(E20,"mmm") -> Apr | K20: =YEAR(E20) -> 2024 | L20: =IF(OR(LEFT(A20,1)="C",D20<0),"Cancelled","Completed") -> Completed | M20: =IF(G20=0,"Unknown",IF(MOD(G20,3)=0,"Wholesale",IF(MOD(G20,2)=0,"Returning","New"))) -> Wholesale
A21: 50020 | B21: 84991 | C21: 60 TEATIME FAIRY CAKE CASES | D21: 12 | E21: 45393.442 | F21: 0.57 | G21: 12797 | H21: Portugal | I21: =D21*F21 -> 6.84 | J21: =TEXT(E21,"mmm") -> Apr | K21: =YEAR(E21) -> 2024 | L21: =IF(OR(LEFT(A21,1)="C",D21<0),"Cancelled","Completed") -> Completed | M21: =IF(G21=0,"Unknown",IF(MOD(G21,3)=0,"Wholesale",IF(MOD(G21,2)=0,"Returning","New"))) -> New
A22: C50021 | B22: 85123A | C22: WHITE HANGING HEART T-LIGHT HOLDER | D22: -6 | E22: 45598.563 | F22: 2.95 | G22: 12851 | H22: Spain | I22: =D22*F22 -> -17.7 | J22: =TEXT(E22,"mmm") -> Nov | K22: =YEAR(E22) -> 2024 | L22: =IF(OR(LEFT(A22,1)="C",D22<0),"Cancelled","Completed") -> Cancelled | M22: =IF(G22=0,"Unknown",IF(MOD(G22,3)=0,"Wholesale",IF(MOD(G22,2)=0,"Returning","New"))) -> New
A23: 50022 | B23: 22423 | C23: REGENCY CAKESTAND 3 TIER | D23: 19 | E23: 45321.504 | F23: 11.22 | G23: 12497 | H23: Germany | I23: =D23*F23 -> 213.18 | J23: =TEXT(E23,"mmm") -> Jan | K23: =YEAR(E23) -> 2024 | L23: =IF(OR(LEFT(A23,1)="C",D23<0),"Cancelled","Completed") -> Completed | M23: =IF(G23=0,"Unknown",IF(MOD(G23,3)=0,"Wholesale",IF(MOD(G23,2)=0,"Returning","New"))) -> New
A24: 50023 | B24: 82494L | C24: WOODEN FRAME ANTIQUE WHITE | D24: 22 | E24: 45356.424 | F24: 3.08 | G24: 12271 | H24: Portugal | I24: =D24*F24 -> 67.76 | J24: =TEXT(E24,"mmm") -> Mar | K24: =YEAR(E24) -> 2024 | L24: =IF(OR(LEFT(A24,1)="C",D24<0),"Cancelled","Completed") -> Completed | M24: =IF(G24=0,"Unknown",IF(MOD(G24,3)=0,"Wholesale",IF(MOD(G24,2)=0,"Returning","New"))) -> New
A25: 50024 | B25: 84991 | C25: 60 TEATIME FAIRY CAKE CASES | D25: 18 | E25: 45508.483 | F25: 0.6 | G25: 12730 | H25: Spain | I25: =D25*F25 -> 10.8 | J25: =TEXT(E25,"mmm") -> Aug | K25: =YEAR(E25) -> 2024 | L25: =IF(OR(LEFT(A25,1)="C",D25<0),"Cancelled","Completed") -> Completed | M25: =IF(G25=0,"Unknown",IF(MOD(G25,3)=0,"Wholesale",IF(MOD(G25,2)=0,"Returning","New"))) -> Returning
A26: 50025 | B26: 22386 | C26: JUMBO BAG PINK POLKADOT | D26: 15 | E26: 45635.599 | F26: 1.97 | G26: 12253 | H26: EIRE | I26: =D26*F26 -> 29.55 | J26: =TEXT(E26,"mmm") -> Dec | K26: =YEAR(E26) -> 2024 | L26: =IF(OR(LEFT(A26,1)="C",D26<0),"Cancelled","Completed") -> Completed | M26: =IF(G26=0,"Unknown",IF(MOD(G26,3)=0,"Wholesale",IF(MOD(G26,2)=0,"Returning","New"))) -> New
A27: 50026 | B27: 84406B | C27: CREAM CUPID HEARTS COAT HANGER | D27: 19 | E27: 45465.348 | F27: 2.9 | G27: 12007 | H27: Germany | I27: =D27*F27 -> 55.1 | J27: =TEXT(E27,"mmm") -> Jun | K27: =YEAR(E27) -> 2024 | L27: =IF(OR(LEFT(A27,1)="C",D27<0),"Cancelled","Completed") -> Completed | M27: =IF(G27=0,"Unknown",IF(MOD(G27,3)=0,"Wholesale",IF(MOD(G27,2)=0,"Returning","New"))) -> New
A28: 50027 | B28: 71053 | C28: WHITE METAL LANTERN | D28: 2 | E28: 45409.381 | F28: 2.97 | G28: 12243 | H28: Spain | I28: =D28*F28 -> 5.94 | J28: =TEXT(E28,"mmm") -> Apr | K28: =YEAR(E28) -> 2024 | L28: =IF(OR(LEFT(A28,1)="C",D28<0),"Cancelled","Completed") -> Completed | M28: =IF(G28=0,"Unknown",IF(MOD(G28,3)=0,"Wholesale",IF(MOD(G28,2)=0,"Returning","New"))) -> Wholesale
A29: 50028 | B29: 23203 | C29: JUMBO BAG DOILEY PATTERNS | D29: 5 | E29: 45401.717 | F29: 2.41 | G29: 12590 | H29: Switzerland | I29: =D29*F29 -> 12.05 | J29: =TEXT(E29,"mmm") -> Apr | K29: =YEAR(E29) -> 2024 | L29: =IF(OR(LEFT(A29,1)="C",D29<0),"Cancelled","Completed") -> Completed | M29: =IF(G29=0,"Unknown",IF(MOD(G29,3)=0,"Wholesale",IF(MOD(G29,2)=0,"Returning","New"))) -> Returning
A30: 50029 | B30: 22423 | C30: REGENCY CAKESTAND 3 TIER | D30: 7 | E30: 45534.622 | F30: 13.78 | G30: 12362 | H30: Belgium | I30: =D30*F30 -> 96.46 | J30: =TEXT(E30,"mmm") -> Aug | K30: =YEAR(E30) -> 2024 | L30: =IF(OR(LEFT(A30,1)="C",D30<0),"Cancelled","Completed") -> Completed | M30: =IF(G30=0,"Unknown",IF(MOD(G30,3)=0,"Wholesale",IF(MOD(G30,2)=0,"Returning","New"))) -> Returning
A31: 50030 | B31: 85099B | C31: JUMBO BAG RED RETROSPOT | D31: 22 | E31: 45531.372 | F31: 2.24 | G31: 12062 | H31: Belgium | I31: =D31*F31 -> 49.28 | J31: =TEXT(E31,"mmm") -> Aug | K31: =YEAR(E31) -> 2024 | L31: =IF(OR(LEFT(A31,1)="C",D31<0),"Cancelled","Completed") -> Completed | M31: =IF(G31=0,"Unknown",IF(MOD(G31,3)=0,"Wholesale",IF(MOD(G31,2)=0,"Returning","New"))) -> Returning
A32: 50031 | B32: 22086 | C32: PAPER CHAIN KIT 50'S CHRISTMAS | D32: 7 | E32: 45347.51 | F32: 2.97 | G32: 12432 | H32: France | I32: =D32*F32 -> 20.79 | J32: =TEXT(E32,"mmm") -> Feb | K32: =YEAR(E32) -> 2024 | L32: =IF(OR(LEFT(A32,1)="C",D32<0),"Cancelled","Completed") -> Completed | M32: =IF(G32=0,"Unknown",IF(MOD(G32,3)=0,"Wholesale",IF(MOD(G32,2)=0,"Returning","New"))) -> Wholesale
A33: 50032 | B33: 47566 | C33: PARTY BUNTING | D33: 3 | E33: 45528.51 | F33: 5.7 | G33: 12563 | H33: Germany | I33: =D33*F33 -> 17.1 | J33: =TEXT(E33,"mmm") -> Aug | K33: =YEAR(E33) -> 2024 | L33: =IF(OR(LEFT(A33,1)="C",D33<0),"Cancelled","Completed") -> Completed | M33: =IF(G33=0,"Unknown",IF(MOD(G33,3)=0,"Wholesale",IF(MOD(G33,2)=0,"Returning","New"))) -> New
A34: 50033 | B34: 71053 | C34: WHITE METAL LANTERN | D34: 1 | E34: 45625.717 | F34: 3.98 | G34: 12869 | H34: EIRE | I34: =D34*F34 -> 3.98 | J34: =TEXT(E34,"mmm") -> Nov | K34: =YEAR(E34) -> 2024 | L34: =IF(OR(LEFT(A34,1)="C",D34<0),"Cancelled","Completed") -> Completed | M34: =IF(G34=0,"Unknown",IF(MOD(G34,3)=0,"Wholesale",IF(MOD(G34,2)=0,"Returning","New"))) -> New
A35: 50034 | B35: 22720 | C35: SET OF 3 CAKE TINS PANTRY DESIGN | D35: 16 | E35: 45500.678 | F35: 4.9 | G35: 12060 | H35: France | I35: =D35*F35 -> 78.4 | J35: =TEXT(E35,"mmm") -> Jul | K35: =YEAR(E35) -> 2024 | L35: =IF(OR(LEFT(A35,1)="C",D35<0),"Cancelled","Completed") -> Completed | M35: =IF(G35=0,"Unknown",IF(MOD(G35,3)=0,"Wholesale",IF(MOD(G35,2)=0,"Returning","New"))) -> Wholesale
A36: 50035 | B36: 22386 | C36: JUMBO BAG PINK POLKADOT | D36: 9 | E36: 45293.61 | F36: 2.19 | G36: 12292 | H36: Belgium | I36: =D36*F36 -> 19.71 | J36: =TEXT(E36,"mmm") -> Jan | K36: =YEAR(E36) -> 2024 | L36: =IF(OR(LEFT(A36,1)="C",D36<0),"Cancelled","Completed") -> Completed | M36: =IF(G36=0,"Unknown",IF(MOD(G36,3)=0,"Wholesale",IF(MOD(G36,2)=0,"Returning","New"))) -> Returning
A37: 50036 | B37: 82494L | C37: WOODEN FRAME ANTIQUE WHITE | D37: 5 | E37: 45630.679 | F37: 2.73 | G37: 12059 | H37: Australia | I37: =D37*F37 -> 13.65 | J37: =TEXT(E37,"mmm") -> Dec | K37: =YEAR(E37) -> 2024 | L37: =IF(OR(LEFT(A37,1)="C",D37<0),"Cancelled","Completed") -> Completed | M37: =IF(G37=0,"Unknown",IF(MOD(G37,3)=0,"Wholesale",IF(MOD(G37,2)=0,"Returning","New"))) -> New
A38: C50037 | B38: 82494L | C38: WOODEN FRAME ANTIQUE WHITE | D38: -2 | E38: 45323.556 | F38: 3.03 | G38: 12873 | H38: Portugal | I38: =D38*F38 -> -6.06 | J38: =TEXT(E38,"mmm") -> Feb | K38: =YEAR(E38) -> 2024 | L38: =IF(OR(LEFT(A38,1)="C",D38<0),"Cancelled","Completed") -> Cancelled | M38: =IF(G38=0,"Unknown",IF(MOD(G38,3)=0,"Wholesale",IF(MOD(G38,2)=0,"Returning","New"))) -> Wholesale
A39: 50038 | B39: 22720 | C39: SET OF 3 CAKE TINS PANTRY DESIGN | D39: 3 | E39: 45321.694 | F39: 4.33 | G39: 12069 | H39: EIRE | I39: =D39*F39 -> 12.99 | J39: =TEXT(E39,"mmm") -> Jan | K39: =YEAR(E39) -> 2024 | L39: =IF(OR(LEFT(A39,1)="C",D39<0),"Cancelled","Completed") -> Completed | M39: =IF(G39=0,"Unknown",IF(MOD(G39,3)=0,"Wholesale",IF(MOD(G39,2)=0,"Returning","New"))) -> Wholesale
A40: 50039 | B40: 22386 | C40: JUMBO BAG PINK POLKADOT | D40: 8 | E40: 45353.738 | F40: 1.68 | G40: 12083 | H40: Belgium | I40: =D40*F40 -> 13.44 | J40: =TEXT(E40,"mmm") -> Mar | K40: =YEAR(E40) -> 2024 | L40: =IF(OR(LEFT(A40,1)="C",D40<0),"Cancelled","Completed") -> Completed | M40: =IF(G40=0,"Unknown",IF(MOD(G40,3)=0,"Wholesale",IF(MOD(G40,2)=0,"Returning","New"))) -> New
A41: 50040 | B41: 84970S | C41: HANGING HEART ZINC T-LIGHT HOLDER | D41: 11 | E41: 45581.705 | F41: 1.15 | G41: 12733 | H41: Netherlands | I41: =D41*F41 -> 12.65 | J41: =TEXT(E41,"mmm") -> Oct | K41: =YEAR(E41) -> 2024 | L41: =IF(OR(LEFT(A41,1)="C",D41<0),"Cancelled","Completed") -> Completed | M41: =IF(G41=0,"Unknown",IF(MOD(G41,3)=0,"Wholesale",IF(MOD(G41,2)=0,"Returning","New"))) -> New
A42: 50041 | B42: 22423 | C42: REGENCY CAKESTAND 3 TIER | D42: 5 | E42: 45427.615 | F42: 12.18 | G42: 12323 | H42: Germany | I42: =D42*F42 -> 60.9 | J42: =TEXT(E42,"mmm") -> May | K42: =YEAR(E42) -> 2024 | L42: =IF(OR(LEFT(A42,1)="C",D42<0),"Cancelled","Completed") -> Completed | M42: =IF(G42=0,"Unknown",IF(MOD(G42,3)=0,"Wholesale",IF(MOD(G42,2)=0,"Returning","New"))) -> New
A43: 50042 | B43: 85123A | C43: WHITE HANGING HEART T-LIGHT HOLDER | D43: 4 | E43: 45526.733 | F43: 2.36 | G43: 12271 | H43: France | I43: =D43*F43 -> 9.44 | J43: =TEXT(E43,"mmm") -> Aug | K43: =YEAR(E43) -> 2024 | L43: =IF(OR(LEFT(A43,1)="C",D43<0),"Cancelled","Completed") -> Completed | M43: =IF(G43=0,"Unknown",IF(MOD(G43,3)=0,"Wholesale",IF(MOD(G43,2)=0,"Returning","New"))) -> New
A44: 50043 | B44: 21212 | C44: PACK OF 72 RETROSPOT CAKE CASES | D44: 12 | E44: 45327.507 | F44: 0.55 | G44: 12556 | H44: Spain | I44: =D44*F44 -> 6.6 | J44: =TEXT(E44,"mmm") -> Feb | K44: =YEAR(E44) -> 2024 | L44: =IF(OR(LEFT(A44,1)="C",D44<0),"Cancelled","Completed") -> Completed | M44: =IF(G44=0,"Unknown",IF(MOD(G44,3)=0,"Wholesale",IF(MOD(G44,2)=0,"Returning","New"))) -> Returning
A45: 50044 | B45: 84991 | C45: 60 TEATIME FAIRY CAKE CASES | D45: 1 | E45: 45626.709 | F45: 0.57 | G45: 12954 | H45: Germany | I45: =D45*F45 -> 0.57 | J45: =TEXT(E45,"mmm") -> Nov | K45: =YEAR(E45) -> 2024 | L45: =IF(OR(LEFT(A45,1)="C",D45<0),"Cancelled","Completed") -> Completed | M45: =IF(G45=0,"Unknown",IF(MOD(G45,3)=0,"Wholesale",IF(MOD(G45,2)=0,"Returning","New"))) -> Wholesale
A46: 50045 | B46: 84879 | C46: ASSORTED COLOUR BIRD ORNAMENT | D46: 4 | E46: 45427.415 | F46: 1.53 | G46: 12288 | H46: Australia | I46: =D46*F46 -> 6.12 | J46: =TEXT(E46,"mmm") -> May | K46: =YEAR(E46) -> 2024 | L46: =IF(OR(LEFT(A46,1)="C",D46<0),"Cancelled","Completed") -> Completed | M46: =IF(G46=0,"Unknown",IF(MOD(G46,3)=0,"Wholesale",IF(MOD(G46,2)=0,"Returning","New"))) -> Wholesale
A47: 50046 | B47: 22727 | C47: ALARM CLOCK BAKELIKE RED | D47: 22 | E47: 45467.478 | F47: 3.53 | G47: 12500 | H47: Spain | I47: =D47*F47 -> 77.66 | J47: =TEXT(E47,"mmm") -> Jun | K47: =YEAR(E47) -> 2024 | L47: =IF(OR(LEFT(A47,1)="C",D47<0),"Cancelled","Completed") -> Completed | M47: =IF(G47=0,"Unknown",IF(MOD(G47,3)=0,"Wholesale",IF(MOD(G47,2)=0,"Returning","New"))) -> Returning
A48: C50047 | B48: 71053 | C48: WHITE METAL LANTERN | D48: -6 | E48: 45339.634 | F48: 3.8 | G48: 12652 | H48: Spain | I48: =D48*F48 -> -22.8 | J48: =TEXT(E48,"mmm") -> Feb | K48: =YEAR(E48) -> 2024 | L48: =IF(OR(LEFT(A48,1)="C",D48<0),"Cancelled","Completed") -> Cancelled | M48: =IF(G48=0,"Unknown",IF(MOD(G48,3)=0,"Wholesale",IF(MOD(G48,2)=0,"Returning","New"))) -> Returning
A49: 50048 | B49: 22720 | C49: SET OF 3 CAKE TINS PANTRY DESIGN | D49: 23 | E49: 45518.725 | F49: 4.22 | G49: 12077 | H49: France | I49: =D49*F49 -> 97.06 | J49: =TEXT(E49,"mmm") -> Aug | K49: =YEAR(E49) -> 2024 | L49: =IF(OR(LEFT(A49,1)="C",D49<0),"Cancelled","Completed") -> Completed | M49: =IF(G49=0,"Unknown",IF(MOD(G49,3)=0,"Wholesale",IF(MOD(G49,2)=0,"Returning","New"))) -> New
A50: 50049 | B50: 82494L | C50: WOODEN FRAME ANTIQUE WHITE | D50: 19 | E50: 45310.596 | F50: 2.95 | G50: 12042 | H50: Spain | I50: =D50*F50 -> 56.05 | J50: =TEXT(E50,"mmm") -> Jan | K50: =YEAR(E50) -> 2024 | L50: =IF(OR(LEFT(A50,1)="C",D50<0),"Cancelled","Completed") -> Completed | M50: =IF(G50=0,"Unknown",IF(MOD(G50,3)=0,"Wholesale",IF(MOD(G50,2)=0,"Returning","New"))) -> Wholesale
A51: 50050 | B51: 21212 | C51: PACK OF 72 RETROSPOT CAKE CASES | D51: 7 | E51: 45312.588 | F51: 0.6 | G51: 12362 | H51: Portugal | I51: =D51*F51 -> 4.2 | J51: =TEXT(E51,"mmm") -> Jan | K51: =YEAR(E51) -> 2024 | L51: =IF(OR(LEFT(A51,1)="C",D51<0),"Cancelled","Completed") -> Completed | M51: =IF(G51=0,"Unknown",IF(MOD(G51,3)=0,"Wholesale",IF(MOD(G51,2)=0,"Returning","New"))) -> Returning
A52: 50051 | B52: 85099B | C52: JUMBO BAG RED RETROSPOT | D52: 8 | E52: 45609.443 | F52: 2.48 | G52: 12830 | H52: France | I52: =D52*F52 -> 19.84 | J52: =TEXT(E52,"mmm") -> Nov | K52: =YEAR(E52) -> 2024 | L52: =IF(OR(LEFT(A52,1)="C",D52<0),"Cancelled","Completed") -> Completed | M52: =IF(G52=0,"Unknown",IF(MOD(G52,3)=0,"Wholesale",IF(MOD(G52,2)=0,"Returning","New"))) -> Returning
A53: 50052 | B53: 85099B | C53: JUMBO BAG RED RETROSPOT | D53: 24 | E53: 45304.46 | F53: 2.34 | G53: 12421 | H53: EIRE | I53: =D53*F53 -> 56.16 | J53: =TEXT(E53,"mmm") -> Jan | K53: =YEAR(E53) -> 2024 | L53: =IF(OR(LEFT(A53,1)="C",D53<0),"Cancelled","Completed") -> Completed | M53: =IF(G53=0,"Unknown",IF(MOD(G53,3)=0,"Wholesale",IF(MOD(G53,2)=0,"Returning","New"))) -> New
A54: 50053 | B54: 47566 | C54: PARTY BUNTING | D54: 13 | E54: 45373.41 | F54: 5.7 | G54: 12227 | H54: EIRE | I54: =D54*F54 -> 74.1 | J54: =TEXT(E54,"mmm") -> Mar | K54: =YEAR(E54) -> 2024 | L54: =IF(OR(LEFT(A54,1)="C",D54<0),"Cancelled","Completed") -> Completed | M54: =IF(G54=0,"Unknown",IF(MOD(G54,3)=0,"Wholesale",IF(MOD(G54,2)=0,"Returning","New"))) -> New
A55: 50054 | B55: 20725 | C55: LUNCH BAG RED RETROSPOT | D55: 8 | E55: 45471.55 | F55: 1.78 | G55: 12408 | H55: Netherlands | I55: =D55*F55 -> 14.24 | J55: =TEXT(E55,"mmm") -> Jun | K55: =YEAR(E55) -> 2024 | L55: =IF(OR(LEFT(A55,1)="C",D55<0),"Cancelled","Completed") -> Completed | M55: =IF(G55=0,"Unknown",IF(MOD(G55,3)=0,"Wholesale",IF(MOD(G55,2)=0,"Returning","New"))) -> Wholesale
A56: 50055 | B56: 47566 | C56: PARTY BUNTING | D56: 12 | E56: 45327.531 | F56: 4.9 | G56: 12863 | H56: Portugal | I56: =D56*F56 -> 58.8 | J56: =TEXT(E56,"mmm") -> Feb | K56: =YEAR(E56) -> 2024 | L56: =IF(OR(LEFT(A56,1)="C",D56<0),"Cancelled","Completed") -> Completed | M56: =IF(G56=0,"Unknown",IF(MOD(G56,3)=0,"Wholesale",IF(MOD(G56,2)=0,"Returning","New"))) -> New
A57: 50056 | B57: 22086 | C57: PAPER CHAIN KIT 50'S CHRISTMAS | D57: 9 | E57: 45306.415 | F57: 3.5 | G57: 12271 | H57: United Kingdom | I57: =D57*F57 -> 31.5 | J57: =TEXT(E57,"mmm") -> Jan | K57: =YEAR(E57) -> 2024 | L57: =IF(OR(LEFT(A57,1)="C",D57<0),"Cancelled","Completed") -> Completed | M57: =IF(G57=0,"Unknown",IF(MOD(G57,3)=0,"Wholesale",IF(MOD(G57,2)=0,"Returning","New"))) -> New
A58: 50057 | B58: 84029G | C58: KNITTED UNION FLAG HOT WATER BOTTLE | D58: 12 | E58: 45597.642 | F58: 3.25 | G58: 12620 | H58: Portugal | I58: =D58*F58 -> 39 | J58: =TEXT(E58,"mmm") -> Nov | K58: =YEAR(E58) -> 2024 | L58: =IF(OR(LEFT(A58,1)="C",D58<0),"Cancelled","Completed") -> Completed | M58: =IF(G58=0,"Unknown",IF(MOD(G58,3)=0,"Wholesale",IF(MOD(G58,2)=0,"Returning","New"))) -> Returning
A59: 50058 | B59: 84029G | C59: KNITTED UNION FLAG HOT WATER BOTTLE | D59: 7 | E59: 45489.743 | F59: 3.72 | G59: 12001 | H59: Portugal | I59: =D59*F59 -> 26.04 | J59: =TEXT(E59,"mmm") -> Jul | K59: =YEAR(E59) -> 2024 | L59: =IF(OR(LEFT(A59,1)="C",D59<0),"Cancelled","Completed") -> Completed | M59: =IF(G59=0,"Unknown",IF(MOD(G59,3)=0,"Wholesale",IF(MOD(G59,2)=0,"Returning","New"))) -> New
A60: 50059 | B60: 82494L | C60: WOODEN FRAME ANTIQUE WHITE | D60: 12 | E60: 45643.473 | F60: 3.49 | G60: 12942 | H60: Netherlands | I60: =D60*F60 -> 41.88 | J60: =TEXT(E60,"mmm") -> Dec | K60: =YEAR(E60) -> 2024 | L60: =IF(OR(LEFT(A60,1)="C",D60<0),"Cancelled","Completed") -> Completed | M60: =IF(G60=0,"Unknown",IF(MOD(G60,3)=0,"Wholesale",IF(MOD(G60,2)=0,"Returning","New"))) -> Wholesale
A61: 50060 | B61: 84991 | C61: 60 TEATIME FAIRY CAKE CASES | D61: 24 | E61: 45452.422 | F61: 0.57 | G61: 12682 | H61: Belgium | I61: =D61*F61 -> 13.68 | J61: =TEXT(E61,"mmm") -> Jun | K61: =YEAR(E61) -> 2024 | L61: =IF(OR(LEFT(A61,1)="C",D61<0),"Cancelled","Completed") -> Completed | M61: =IF(G61=0,"Unknown",IF(MOD(G61,3)=0,"Wholesale",IF(MOD(G61,2)=0,"Returning","New"))) -> Returning
A62: 50061 | B62: 22086 | C62: PAPER CHAIN KIT 50'S CHRISTMAS | D62: 18 | E62: 45498.543 | F62: 2.94 | G62: 12962 | H62: Belgium | I62: =D62*F62 -> 52.92 | J62: =TEXT(E62,"mmm") -> Jul | K62: =YEAR(E62) -> 2024 | L62: =IF(OR(LEFT(A62,1)="C",D62<0),"Cancelled","Completed") -> Completed | M62: =IF(G62=0,"Unknown",IF(MOD(G62,3)=0,"Wholesale",IF(MOD(G62,2)=0,"Returning","New"))) -> Returning
A63: 50062 | B63: 22720 | C63: SET OF 3 CAKE TINS PANTRY DESIGN | D63: 10 | E63: 45607.738 | F63: 5.65 | G63: 12311 | H63: Spain | I63: =D63*F63 -> 56.5 | J63: =TEXT(E63,"mmm") -> Nov | K63: =YEAR(E63) -> 2024 | L63: =IF(OR(LEFT(A63,1)="C",D63<0),"Cancelled","Completed") -> Completed | M63: =IF(G63=0,"Unknown",IF(MOD(G63,3)=0,"Wholesale",IF(MOD(G63,2)=0,"Returning","New"))) -> New
A64: 50063 | B64: 22727 | C64: ALARM CLOCK BAKELIKE RED | D64: 20 | E64: 45512.745 | F64: 3.8 | G64: 12452 | H64: EIRE | I64: =D64*F64 -> 76 | J64: =TEXT(E64,"mmm") -> Aug | K64: =YEAR(E64) -> 2024 | L64: =IF(OR(LEFT(A64,1)="C",D64<0),"Cancelled","Completed") -> Completed | M64: =IF(G64=0,"Unknown",IF(MOD(G64,3)=0,"Wholesale",IF(MOD(G64,2)=0,"Returning","New"))) -> Returning
A65: 50064 | B65: POST | C65: POSTAGE | D65: 22 | E65: 45534.453 | F65: 18.55 | G65: 12648 | H65: Australia | I65: =D65*F65 -> 408.1 | J65: =TEXT(E65,"mmm") -> Aug | K65: =YEAR(E65) -> 2024 | L65: =IF(OR(LEFT(A65,1)="C",D65<0),"Cancelled","Completed") -> Completed | M65: =IF(G65=0,"Unknown",IF(MOD(G65,3)=0,"Wholesale",IF(MOD(G65,2)=0,"Returning","New"))) -> Wholesale
A66: 50065 | B66: 22086 | C66: PAPER CHAIN KIT 50'S CHRISTMAS | D66: 22 | E66: 45339.5 | F66: 3.34 | G66: 12150 | H66: United Kingdom | I66: =D66*F66 -> 73.48 | J66: =TEXT(E66,"mmm") -> Feb | K66: =YEAR(E66) -> 2024 | L66: =IF(OR(LEFT(A66,1)="C",D66<0),"Cancelled","Completed") -> Completed | M66: =IF(G66=0,"Unknown",IF(MOD(G66,3)=0,"Wholesale",IF(MOD(G66,2)=0,"Returning","New"))) -> Wholesale
A67: 50066 | B67: 71053 | C67: WHITE METAL LANTERN | D67: 20 | E67: 45417.671 | F67: 2.97 | G67: 12424 | H67: Australia | I67: =D67*F67 -> 59.4 | J67: =TEXT(E67,"mmm") -> May | K67: =YEAR(E67) -> 2024 | L67: =IF(OR(LEFT(A67,1)="C",D67<0),"Cancelled","Completed") -> Completed | M67: =IF(G67=0,"Unknown",IF(MOD(G67,3)=0,"Wholesale",IF(MOD(G67,2)=0,"Returning","New"))) -> Returning
A68: 50067 | B68: 22727 | C68: ALARM CLOCK BAKELIKE RED | D68: 16 | E68: 45648.606 | F68: 3.38 | G68: 12704 | H68: United Kingdom | I68: =D68*F68 -> 54.08 | J68: =TEXT(E68,"mmm") -> Dec | K68: =YEAR(E68) -> 2024 | L68: =IF(OR(LEFT(A68,1)="C",D68<0),"Cancelled","Completed") -> Completed | M68: =IF(G68=0,"Unknown",IF(MOD(G68,3)=0,"Wholesale",IF(MOD(G68,2)=0,"Returning","New"))) -> Returning
A69: 50068 | B69: 84029G | C69: KNITTED UNION FLAG HOT WATER BOTTLE | D69: 6 | E69: 45509.489 | F69: 3.71 | G69: 12475 | H69: United Kingdom | I69: =D69*F69 -> 22.26 | J69: =TEXT(E69,"mmm") -> Aug | K69: =YEAR(E69) -> 2024 | L69: =IF(OR(LEFT(A69,1)="C",D69<0),"Cancelled","Completed") -> Completed | M69: =IF(G69=0,"Unknown",IF(MOD(G69,3)=0,"Wholesale",IF(MOD(G69,2)=0,"Returning","New"))) -> New
A70: 50069 | B70: 82494L | C70: WOODEN FRAME ANTIQUE WHITE | D70: 15 | E70: 45419.419 | F70: 2.99 | G70: 12543 | H70: Portugal | I70: =D70*F70 -> 44.85 | J70: =TEXT(E70,"mmm") -> May | K70: =YEAR(E70) -> 2024 | L70: =IF(OR(LEFT(A70,1)="C",D70<0),"Cancelled","Completed") -> Completed | M70: =IF(G70=0,"Unknown",IF(MOD(G70,3)=0,"Wholesale",IF(MOD(G70,2)=0,"Returning","New"))) -> Wholesale
A71: 50070 | B71: 84991 | C71: 60 TEATIME FAIRY CAKE CASES | D71: 20 | E71: 45454.648 | F71: 0.64 | G71: 12436 | H71: Portugal | I71: =D71*F71 -> 12.8 | J71: =TEXT(E71,"mmm") -> Jun | K71: =YEAR(E71) -> 2024 | L71: =IF(OR(LEFT(A71,1)="C",D71<0),"Cancelled","Completed") -> Completed | M71: =IF(G71=0,"Unknown",IF(MOD(G71,3)=0,"Wholesale",IF(MOD(G71,2)=0,"Returning","New"))) -> Returning
A72: 50071 | B72: 20725 | C72: LUNCH BAG RED RETROSPOT | D72: 15 | E72: 45373.671 | F72: 1.55 | G72: 12652 | H72: Spain | I72: =D72*F72 -> 23.25 | J72: =TEXT(E72,"mmm") -> Mar | K72: =YEAR(E72) -> 2024 | L72: =IF(OR(LEFT(A72,1)="C",D72<0),"Cancelled","Completed") -> Completed | M72: =IF(G72=0,"Unknown",IF(MOD(G72,3)=0,"Wholesale",IF(MOD(G72,2)=0,"Returning","New"))) -> Returning
A73: 50072 | B73: POST | C73: POSTAGE | D73: 1 | E73: 45540.503 | F73: 19.8 | G73: 12240 | H73: Spain | I73: =D73*F73 -> 19.8 | J73: =TEXT(E73,"mmm") -> Sep | K73: =YEAR(E73) -> 2024 | L73: =IF(OR(LEFT(A73,1)="C",D73<0),"Cancelled","Completed") -> Completed | M73: =IF(G73=0,"Unknown",IF(MOD(G73,3)=0,"Wholesale",IF(MOD(G73,2)=0,"Returning","New"))) -> Wholesale
A74: 50073 | B74: 22086 | C74: PAPER CHAIN KIT 50'S CHRISTMAS | D74: 3 | E74: 45455.717 | F74: 2.75 | G74: 12710 | H74: France | I74: =D74*F74 -> 8.25 | J74: =TEXT(E74,"mmm") -> Jun | K74: =YEAR(E74) -> 2024 | L74: =IF(OR(LEFT(A74,1)="C",D74<0),"Cancelled","Completed") -> Completed | M74: =IF(G74=0,"Unknown",IF(MOD(G74,3)=0,"Wholesale",IF(MOD(G74,2)=0,"Returning","New"))) -> Returning
A75: 50074 | B75: 22727 | C75: ALARM CLOCK BAKELIKE RED | D75: 14 | E75: 45324.628 | F75: 3.8 | G75: 12063 | H75: EIRE | I75: =D75*F75 -> 53.2 | J75: =TEXT(E75,"mmm") -> Feb | K75: =YEAR(E75) -> 2024 | L75: =IF(OR(LEFT(A75,1)="C",D75<0),"Cancelled","Completed") -> Completed | M75: =IF(G75=0,"Unknown",IF(MOD(G75,3)=0,"Wholesale",IF(MOD(G75,2)=0,"Returning","New"))) -> Wholesale
A76: C50075 | B76: 85099B | C76: JUMBO BAG RED RETROSPOT | D76: -7 | E76: 45491.749 | F76: 2.12 | G76: 12965 | H76: Netherlands | I76: =D76*F76 -> -14.84 | J76: =TEXT(E76,"mmm") -> Jul | K76: =YEAR(E76) -> 2024 | L76: =IF(OR(LEFT(A76,1)="C",D76<0),"Cancelled","Completed") -> Cancelled | M76: =IF(G76=0,"Unknown",IF(MOD(G76,3)=0,"Wholesale",IF(MOD(G76,2)=0,"Returning","New"))) -> New
A77: 50076 | B77: 22960 | C77: JAM MAKING SET WITH JARS | D77: 18 | E77: 45491.631 | F77: 4.42 | G77: 12617 | H77: EIRE | I77: =D77*F77 -> 79.56 | J77: =TEXT(E77,"mmm") -> Jul | K77: =YEAR(E77) -> 2024 | L77: =IF(OR(LEFT(A77,1)="C",D77<0),"Cancelled","Completed") -> Completed | M77: =IF(G77=0,"Unknown",IF(MOD(G77,3)=0,"Wholesale",IF(MOD(G77,2)=0,"Returning","New"))) -> New
A78: 50077 | B78: 23203 | C78: JUMBO BAG DOILEY PATTERNS | D78: 14 | E78: 45404.527 | F78: 2.05 | G78: 12684 | H78: Belgium | I78: =D78*F78 -> 28.7 | J78: =TEXT(E78,"mmm") -> Apr | K78: =YEAR(E78) -> 2024 | L78: =IF(OR(LEFT(A78,1)="C",D78<0),"Cancelled","Completed") -> Completed | M78: =IF(G78=0,"Unknown",IF(MOD(G78,3)=0,"Wholesale",IF(MOD(G78,2)=0,"Returning","New"))) -> Wholesale
A79: 50078 | B79: 22720 | C79: SET OF 3 CAKE TINS PANTRY DESIGN | D79: 20 | E79: 45531.424 | F79: 5.78 | G79: 12606 | H79: Australia | I79: =D79*F79 -> 115.6 | J79: =TEXT(E79,"mmm") -> Aug | K79: =YEAR(E79) -> 2024 | L79: =IF(OR(LEFT(A79,1)="C",D79<0),"Cancelled","Completed") -> Completed | M79: =IF(G79=0,"Unknown",IF(MOD(G79,3)=0,"Wholesale",IF(MOD(G79,2)=0,"Returning","New"))) -> Wholesale
A80: 50079 | B80: 85123A | C80: WHITE HANGING HEART T-LIGHT HOLDER | D80: 5 | E80: 45334.637 | F80: 2.33 | G80: 12266 | H80: Belgium | I80: =D80*F80 -> 11.65 | J80: =TEXT(E80,"mmm") -> Feb | K80: =YEAR(E80) -> 2024 | L80: =IF(OR(LEFT(A80,1)="C",D80<0),"Cancelled","Completed") -> Completed | M80: =IF(G80=0,"Unknown",IF(MOD(G80,3)=0,"Wholesale",IF(MOD(G80,2)=0,"Returning","New"))) -> Returning
A81: 50080 | B81: 22086 | C81: PAPER CHAIN KIT 50'S CHRISTMAS | D81: 11 | E81: 45400.656 | F81: 3.42 | G81: 12284 | H81: Belgium | I81: =D81*F81 -> 37.62 | J81: =TEXT(E81,"mmm") -> Apr | K81: =YEAR(E81) -> 2024 | L81: =IF(OR(LEFT(A81,1)="C",D81<0),"Cancelled","Completed") -> Completed | M81: =IF(G81=0,"Unknown",IF(MOD(G81,3)=0,"Wholesale",IF(MOD(G81,2)=0,"Returning","New"))) -> Returning
A82: 50081 | B82: 47566 | C82: PARTY BUNTING | D82: 1 | E82: 45333.667 | F82: 4.3 | G82: 12974 | H82: Netherlands | I82: =D82*F82 -> 4.3 | J82: =TEXT(E82,"mmm") -> Feb | K82: =YEAR(E82) -> 2024 | L82: =IF(OR(LEFT(A82,1)="C",D82<0),"Cancelled","Completed") -> Completed | M82: =IF(G82=0,"Unknown",IF(MOD(G82,3)=0,"Wholesale",IF(MOD(G82,2)=0,"Returning","New"))) -> Returning
A83: C50082 | B83: 22423 | C83: REGENCY CAKESTAND 3 TIER | D83: -1 | E83: 45624.382 | F83: 15.08 | G83: 12204 | H83: United Kingdom | I83: =D83*F83 -> -15.08 | J83: =TEXT(E83,"mmm") -> Nov | K83: =YEAR(E83) -> 2024 | L83: =IF(OR(LEFT(A83,1)="C",D83<0),"Cancelled","Completed") -> Cancelled | M83: =IF(G83=0,"Unknown",IF(MOD(G83,3)=0,"Wholesale",IF(MOD(G83,2)=0,"Returning","New"))) -> Wholesale
A84: 50083 | B84: 84991 | C84: 60 TEATIME FAIRY CAKE CASES | D84: 5 | E84: 45370.503 | F84: 0.49 | G84: 12970 | H84: EIRE | I84: =D84*F84 -> 2.45 | J84: =TEXT(E84,"mmm") -> Mar | K84: =YEAR(E84) -> 2024 | L84: =IF(OR(LEFT(A84,1)="C",D84<0),"Cancelled","Completed") -> Completed | M84: =IF(G84=0,"Unknown",IF(MOD(G84,3)=0,"Wholesale",IF(MOD(G84,2)=0,"Returning","New"))) -> Returning
A85: 50084 | B85: 20725 | C85: LUNCH BAG RED RETROSPOT | D85: 12 | E85: 45650.515 | F85: 1.75 | G85: 12765 | H85: Germany | I85: =D85*F85 -> 21 | J85: =TEXT(E85,"mmm") -> Dec | K85: =YEAR(E85) -> 2024 | L85: =IF(OR(LEFT(A85,1)="C",D85<0),"Cancelled","Completed") -> Completed | M85: =IF(G85=0,"Unknown",IF(MOD(G85,3)=0,"Wholesale",IF(MOD(G85,2)=0,"Returning","New"))) -> Wholesale
A86: C50085 | B86: 22720 | C86: SET OF 3 CAKE TINS PANTRY DESIGN | D86: -5 | E86: 45451.41 | F86: 5.21 | G86: 12929 | H86: Belgium | I86: =D86*F86 -> -26.05 | J86: =TEXT(E86,"mmm") -> Jun | K86: =YEAR(E86) -> 2024 | L86: =IF(OR(LEFT(A86,1)="C",D86<0),"Cancelled","Completed") -> Cancelled | M86: =IF(G86=0,"Unknown",IF(MOD(G86,3)=0,"Wholesale",IF(MOD(G86,2)=0,"Returning","New"))) -> New
A87: 50086 | B87: 22386 | C87: JUMBO BAG PINK POLKADOT | D87: 19 | E87: 45393.387 | F87: 2.09 | G87: 12104 | H87: Spain | I87: =D87*F87 -> 39.71 | J87: =TEXT(E87,"mmm") -> Apr | K87: =YEAR(E87) -> 2024 | L87: =IF(OR(LEFT(A87,1)="C",D87<0),"Cancelled","Completed") -> Completed | M87: =IF(G87=0,"Unknown",IF(MOD(G87,3)=0,"Wholesale",IF(MOD(G87,2)=0,"Returning","New"))) -> Returning
A88: 50087 | B88: 84991 | C88: 60 TEATIME FAIRY CAKE CASES | D88: 2 | E88: 45353.735 | F88: 0.55 | G88: 12379 | H88: Germany | I88: =D88*F88 -> 1.1 | J88: =TEXT(E88,"mmm") -> Mar | K88: =YEAR(E88) -> 2024 | L88: =IF(OR(LEFT(A88,1)="C",D88<0),"Cancelled","Completed") -> Completed | M88: =IF(G88=0,"Unknown",IF(MOD(G88,3)=0,"Wholesale",IF(MOD(G88,2)=0,"Returning","New"))) -> New
A89: 50088 | B89: POST | C89: POSTAGE | D89: 1 | E89: 45623.576 | F89: 20.48 | G89: 12108 | H89: Belgium | I89: =D89*F89 -> 20.48 | J89: =TEXT(E89,"mmm") -> Nov | K89: =YEAR(E89) -> 2024 | L89: =IF(OR(LEFT(A89,1)="C",D89<0),"Cancelled","Completed") -> Completed | M89: =IF(G89=0,"Unknown",IF(MOD(G89,3)=0,"Wholesale",IF(MOD(G89,2)=0,"Returning","New"))) -> Wholesale
A90: 50089 | B90: 21212 | C90: PACK OF 72 RETROSPOT CAKE CASES | D90: 23 | E90: 45617.66 | F90: 0.5 | G90: 12534 | H90: Spain | I90: =D90*F90 -> 11.5 | J90: =TEXT(E90,"mmm") -> Nov | K90: =YEAR(E90) -> 2024 | L90: =IF(OR(LEFT(A90,1)="C",D90<0),"Cancelled","Completed") -> Completed | M90: =IF(G90=0,"Unknown",IF(MOD(G90,3)=0,"Wholesale",IF(MOD(G90,2)=0,"Returning","New"))) -> Wholesale
A91: 50090 | B91: 84991 | C91: 60 TEATIME FAIRY CAKE CASES | D91: 15 | E91: 45567.677 | F91: 0.61 | G91: 12274 | H91: Netherlands | I91: =D91*F91 -> 9.15 | J91: =TEXT(E91,"mmm") -> Oct | K91: =YEAR(E91) -> 2024 | L91: =IF(OR(LEFT(A91,1)="C",D91<0),"Cancelled","Completed") -> Completed | M91: =IF(G91=0,"Unknown",IF(MOD(G91,3)=0,"Wholesale",IF(MOD(G91,2)=0,"Returning","New"))) -> Returning
A92: 50091 | B92: 22423 | C92: REGENCY CAKESTAND 3 TIER | D92: 15 | E92: 45336.531 | F92: 12.91 | G92: 12624 | H92: Belgium | I92: =D92*F92 -> 193.65 | J92: =TEXT(E92,"mmm") -> Feb | K92: =YEAR(E92) -> 2024 | L92: =IF(OR(LEFT(A92,1)="C",D92<0),"Cancelled","Completed") -> Completed | M92: =IF(G92=0,"Unknown",IF(MOD(G92,3)=0,"Wholesale",IF(MOD(G92,2)=0,"Returning","New"))) -> Wholesale
A93: 50092 | B93: 22086 | C93: PAPER CHAIN KIT 50'S CHRISTMAS | D93: 11 | E93: 45306.685 | F93: 2.73 | G93: 12816 | H93: Spain | I93: =D93*F93 -> 30.03 | J93: =TEXT(E93,"mmm") -> Jan | K93: =YEAR(E93) -> 2024 | L93: =IF(OR(LEFT(A93,1)="C",D93<0),"Cancelled","Completed") -> Completed | M93: =IF(G93=0,"Unknown",IF(MOD(G93,3)=0,"Wholesale",IF(MOD(G93,2)=0,"Returning","New"))) -> Wholesale
A94: C50093 | B94: 22086 | C94: PAPER CHAIN KIT 50'S CHRISTMAS | D94: -4 | E94: 45435.529 | F94: 2.6 | G94: 12737 | H94: Belgium | I94: =D94*F94 -> -10.4 | J94: =TEXT(E94,"mmm") -> May | K94: =YEAR(E94) -> 2024 | L94: =IF(OR(LEFT(A94,1)="C",D94<0),"Cancelled","Completed") -> Cancelled | M94: =IF(G94=0,"Unknown",IF(MOD(G94,3)=0,"Wholesale",IF(MOD(G94,2)=0,"Returning","New"))) -> New
A95: 50094 | B95: 23203 | C95: JUMBO BAG DOILEY PATTERNS | D95: 23 | E95: 45576.504 | F95: 2.29 | G95: 12458 | H95: United Kingdom | I95: =D95*F95 -> 52.67 | J95: =TEXT(E95,"mmm") -> Oct | K95: =YEAR(E95) -> 2024 | L95: =IF(OR(LEFT(A95,1)="C",D95<0),"Cancelled","Completed") -> Completed | M95: =IF(G95=0,"Unknown",IF(MOD(G95,3)=0,"Wholesale",IF(MOD(G95,2)=0,"Returning","New"))) -> Returning
A96: 50095 | B96: 84406B | C96: CREAM CUPID HEARTS COAT HANGER | D96: 13 | E96: 45442.49 | F96: 2.63 | G96: 12595 | H96: Netherlands | I96: =D96*F96 -> 34.19 | J96: =TEXT(E96,"mmm") -> May | K96: =YEAR(E96) -> 2024 | L96: =IF(OR(LEFT(A96,1)="C",D96<0),"Cancelled","Completed") -> Completed | M96: =IF(G96=0,"Unknown",IF(MOD(G96,3)=0,"Wholesale",IF(MOD(G96,2)=0,"Returning","New"))) -> New
A97: 50096 | B97: 23203 | C97: JUMBO BAG DOILEY PATTERNS | D97: 12 | E97: 45575.71 | F97: 2.31 | G97: 12338 | H97: Netherlands | I97: =D97*F97 -> 27.72 | J97: =TEXT(E97,"mmm") -> Oct | K97: =YEAR(E97) -> 2024 | L97: =IF(OR(LEFT(A97,1)="C",D97<0),"Cancelled","Completed") -> Completed | M97: =IF(G97=0,"Unknown",IF(MOD(G97,3)=0,"Wholesale",IF(MOD(G97,2)=0,"Returning","New"))) -> Returning
A98: 50097 | B98: 20725 | C98: LUNCH BAG RED RETROSPOT | D98: 9 | E98: 45430.551 | F98: 1.82 | G98: 12323 | H98: Germany | I98: =D98*F98 -> 16.38 | J98: =TEXT(E98,"mmm") -> May | K98: =YEAR(E98) -> 2024 | L98: =IF(OR(LEFT(A98,1)="C",D98<0),"Cancelled","Completed") -> Completed | M98: =IF(G98=0,"Unknown",IF(MOD(G98,3)=0,"Wholesale",IF(MOD(G98,2)=0,"Returning","New"))) -> New
A99: 50098 | B99: 82494L | C99: WOODEN FRAME ANTIQUE WHITE | D99: 7 | E99: 45645.465 | F99: 3.01 | G99: 12741 | H99: Australia | I99: =D99*F99 -> 21.07 | J99: =TEXT(E99,"mmm") -> Dec | K99: =YEAR(E99) -> 2024 | L99: =IF(OR(LEFT(A99,1)="C",D99<0),"Cancelled","Completed") -> Completed | M99: =IF(G99=0,"Unknown",IF(MOD(G99,3)=0,"Wholesale",IF(MOD(G99,2)=0,"Returning","New"))) -> Wholesale
A100: 50099 | B100: POST | C100: POSTAGE | D100: 4 | E100: 45597.534 | F100: 17.17 | G100: 12369 | H100: France | I100: =D100*F100 -> 68.68 | J100: =TEXT(E100,"mmm") -> Nov | K100: =YEAR(E100) -> 2024 | L100: =IF(OR(LEFT(A100,1)="C",D100<0),"Cancelled","Completed") -> Completed | M100: =IF(G100=0,"Unknown",IF(MOD(G100,3)=0,"Wholesale",IF(MOD(G100,2)=0,"Returning","New"))) -> Wholesale
...

Sheet Pivot_Summary
A1: Pivot-Style Summary Tables
A3: 1) Revenue by Country | G3: 2) Monthly Revenue
A4: Country | B4: Orders | C4: Units | D4: Revenue | E4: Average Order Value | G4: Month | H4: Revenue | I4: Units | J4: Orders
A5: United Kingdom | B5: =COUNTIFS(Clean_Data!$H:$H,A5,Clean_Data!$L:$L,"Completed") -> 34 | C5: =SUMIFS(Clean_Data!$D:$D,Clean_Data!$H:$H,A5,Clean_Data!$L:$L,"Completed") -> 379 | D5: =SUMIFS(Clean_Data!$I:$I,Clean_Data!$H:$H,A5,Clean_Data!$L:$L,"Completed") -> 1695.54 | E5: =IFERROR(D5/B5,0) -> 49.868824 | G5: Jan | H5: =SUMIFS(Clean_Data!$I:$I,Clean_Data!$J:$J,G5,Clean_Data!$L:$L,"Completed") -> 1965.19 | I5: =SUMIFS(Clean_Data!$D:$D,Clean_Data!$J:$J,G5,Clean_Data!$L:$L,"Completed") -> 475 | J5: =COUNTIFS(Clean_Data!$J:$J,G5,Clean_Data!$L:$L,"Completed") -> 39
A6: Germany | B6: =COUNTIFS(Clean_Data!$H:$H,A6,Clean_Data!$L:$L,"Completed") -> 49 | C6: =SUMIFS(Clean_Data!$D:$D,Clean_Data!$H:$H,A6,Clean_Data!$L:$L,"Completed") -> 613 | D6: =SUMIFS(Clean_Data!$I:$I,Clean_Data!$H:$H,A6,Clean_Data!$L:$L,"Completed") -> 2467.38 | E6: =IFERROR(D6/B6,0) -> 50.354694 | G6: Feb | H6: =SUMIFS(Clean_Data!$I:$I,Clean_Data!$J:$J,G6,Clean_Data!$L:$L,"Completed") -> 1718.96 | I6: =SUMIFS(Clean_Data!$D:$D,Clean_Data!$J:$J,G6,Clean_Data!$L:$L,"Completed") -> 445 | J6: =COUNTIFS(Clean_Data!$J:$J,G6,Clean_Data!$L:$L,"Completed") -> 39
A7: France | B7: =COUNTIFS(Clean_Data!$H:$H,A7,Clean_Data!$L:$L,"Completed") -> 49 | C7: =SUMIFS(Clean_Data!$D:$D,Clean_Data!$H:$H,A7,Clean_Data!$L:$L,"Completed") -> 593 | D7: =SUMIFS(Clean_Data!$I:$I,Clean_Data!$H:$H,A7,Clean_Data!$L:$L,"Completed") -> 2071.56 | E7: =IFERROR(D7/B7,0) -> 42.276735 | G7: Mar | H7: =SUMIFS(Clean_Data!$I:$I,Clean_Data!$J:$J,G7,Clean_Data!$L:$L,"Completed") -> 1313.35 | I7: =SUMIFS(Clean_Data!$D:$D,Clean_Data!$J:$J,G7,Clean_Data!$L:$L,"Completed") -> 458 | J7: =COUNTIFS(Clean_Data!$J:$J,G7,Clean_Data!$L:$L,"Completed") -> 39
A8: EIRE | B8: =COUNTIFS(Clean_Data!$H:$H,A8,Clean_Data!$L:$L,"Completed") -> 42 | C8: =SUMIFS(Clean_Data!$D:$D,Clean_Data!$H:$H,A8,Clean_Data!$L:$L,"Completed") -> 532 | D8: =SUMIFS(Clean_Data!$I:$I,Clean_Data!$H:$H,A8,Clean_Data!$L:$L,"Completed") -> 1997.95 | E8: =IFERROR(D8/B8,0) -> 47.570238 | G8: Apr | H8: =SUMIFS(Clean_Data!$I:$I,Clean_Data!$J:$J,G8,Clean_Data!$L:$L,"Completed") -> 1051.24 | I8: =SUMIFS(Clean_Data!$D:$D,Clean_Data!$J:$J,G8,Clean_Data!$L:$L,"Completed") -> 363 | J8: =COUNTIFS(Clean_Data!$J:$J,G8,Clean_Data!$L:$L,"Completed") -> 32
A9: Spain | B9: =COUNTIFS(Clean_Data!$H:$H,A9,Clean_Data!$L:$L,"Completed") -> 43 | C9: =SUMIFS(Clean_Data!$D:$D,Clean_Data!$H:$H,A9,Clean_Data!$L:$L,"Completed") -> 518 | D9: =SUMIFS(Clean_Data!$I:$I,Clean_Data!$H:$H,A9,Clean_Data!$L:$L,"Completed") -> 1398.13 | E9: =IFERROR(D9/B9,0) -> 32.514651 | G9: May | H9: =SUMIFS(Clean_Data!$I:$I,Clean_Data!$J:$J,G9,Clean_Data!$L:$L,"Completed") -> 1510.53 | I9: =SUMIFS(Clean_Data!$D:$D,Clean_Data!$J:$J,G9,Clean_Data!$L:$L,"Completed") -> 432 | J9: =COUNTIFS(Clean_Data!$J:$J,G9,Clean_Data!$L:$L,"Completed") -> 35
A10: Netherlands | B10: =COUNTIFS(Clean_Data!$H:$H,A10,Clean_Data!$L:$L,"Completed") -> 57 | C10: =SUMIFS(Clean_Data!$D:$D,Clean_Data!$H:$H,A10,Clean_Data!$L:$L,"Completed") -> 729 | D10: =SUMIFS(Clean_Data!$I:$I,Clean_Data!$H:$H,A10,Clean_Data!$L:$L,"Completed") -> 3449.53 | E10: =IFERROR(D10/B10,0) -> 60.51807 | G10: Jun | H10: =SUMIFS(Clean_Data!$I:$I,Clean_Data!$J:$J,G10,Clean_Data!$L:$L,"Completed") -> 2163.28 | I10: =SUMIFS(Clean_Data!$D:$D,Clean_Data!$J:$J,G10,Clean_Data!$L:$L,"Completed") -> 543 | J10: =COUNTIFS(Clean_Data!$J:$J,G10,Clean_Data!$L:$L,"Completed") -> 40
A11: Belgium | B11: =COUNTIFS(Clean_Data!$H:$H,A11,Clean_Data!$L:$L,"Completed") -> 46 | C11: =SUMIFS(Clean_Data!$D:$D,Clean_Data!$H:$H,A11,Clean_Data!$L:$L,"Completed") -> 559 | D11: =SUMIFS(Clean_Data!$I:$I,Clean_Data!$H:$H,A11,Clean_Data!$L:$L,"Completed") -> 2390.51 | E11: =IFERROR(D11/B11,0) -> 51.967609 | G11: Jul | H11: =SUMIFS(Clean_Data!$I:$I,Clean_Data!$J:$J,G11,Clean_Data!$L:$L,"Completed") -> 2368.88 | I11: =SUMIFS(Clean_Data!$D:$D,Clean_Data!$J:$J,G11,Clean_Data!$L:$L,"Completed") -> 516 | J11: =COUNTIFS(Clean_Data!$J:$J,G11,Clean_Data!$L:$L,"Completed") -> 45
A12: Switzerland | B12: =COUNTIFS(Clean_Data!$H:$H,A12,Clean_Data!$L:$L,"Completed") -> 42 | C12: =SUMIFS(Clean_Data!$D:$D,Clean_Data!$H:$H,A12,Clean_Data!$L:$L,"Completed") -> 488 | D12: =SUMIFS(Clean_Data!$I:$I,Clean_Data!$H:$H,A12,Clean_Data!$L:$L,"Completed") -> 2594.1 | E12: =IFERROR(D12/B12,0) -> 61.764286 | G12: Aug | H12: =SUMIFS(Clean_Data!$I:$I,Clean_Data!$J:$J,G12,Clean_Data!$L:$L,"Completed") -> 3634.62 | I12: =SUMIFS(Clean_Data!$D:$D,Clean_Data!$J:$J,G12,Clean_Data!$L:$L,"Completed") -> 668 | J12: =COUNTIFS(Clean_Data!$J:$J,G12,Clean_Data!$L:$L,"Completed") -> 45
A13: Portugal | B13: =COUNTIFS(Clean_Data!$H:$H,A13,Clean_Data!$L:$L,"Completed") -> 51 | C13: =SUMIFS(Clean_Data!$D:$D,Clean_Data!$H:$H,A13,Clean_Data!$L:$L,"Completed") -> 691 | D13: =SUMIFS(Clean_Data!$I:$I,Clean_Data!$H:$H,A13,Clean_Data!$L:$L,"Completed") -> 3175.02 | E13: =IFERROR(D13/B13,0) -> 62.255294 | G13: Sep | H13: =SUMIFS(Clean_Data!$I:$I,Clean_Data!$J:$J,G13,Clean_Data!$L:$L,"Completed") -> 2073.57 | I13: =SUMIFS(Clean_Data!$D:$D,Clean_Data!$J:$J,G13,Clean_Data!$L:$L,"Completed") -> 492 | J13: =COUNTIFS(Clean_Data!$J:$J,G13,Clean_Data!$L:$L,"Completed") -> 40
A14: Australia | B14: =COUNTIFS(Clean_Data!$H:$H,A14,Clean_Data!$L:$L,"Completed") -> 48 | C14: =SUMIFS(Clean_Data!$D:$D,Clean_Data!$H:$H,A14,Clean_Data!$L:$L,"Completed") -> 572 | D14: =SUMIFS(Clean_Data!$I:$I,Clean_Data!$H:$H,A14,Clean_Data!$L:$L,"Completed") -> 2256.48 | E14: =IFERROR(D14/B14,0) -> 47.01 | G14: Oct | H14: =SUMIFS(Clean_Data!$I:$I,Clean_Data!$J:$J,G14,Clean_Data!$L:$L,"Completed") -> 2117.09 | I14: =SUMIFS(Clean_Data!$D:$D,Clean_Data!$J:$J,G14,Clean_Data!$L:$L,"Completed") -> 467 | J14: =COUNTIFS(Clean_Data!$J:$J,G14,Clean_Data!$L:$L,"Completed") -> 36
G15: Nov | H15: =SUMIFS(Clean_Data!$I:$I,Clean_Data!$J:$J,G15,Clean_Data!$L:$L,"Completed") -> 1533.43 | I15: =SUMIFS(Clean_Data!$D:$D,Clean_Data!$J:$J,G15,Clean_Data!$L:$L,"Completed") -> 364 | J15: =COUNTIFS(Clean_Data!$J:$J,G15,Clean_Data!$L:$L,"Completed") -> 35
G16: Dec | H16: =SUMIFS(Clean_Data!$I:$I,Clean_Data!$J:$J,G16,Clean_Data!$L:$L,"Completed") -> 2046.06 | I16: =SUMIFS(Clean_Data!$D:$D,Clean_Data!$J:$J,G16,Clean_Data!$L:$L,"Completed") -> 451 | J16: =COUNTIFS(Clean_Data!$J:$J,G16,Clean_Data!$L:$L,"Completed") -> 36
A17: 3) Revenue by Customer Segment
A18: Segment | B18: Orders | C18: Revenue
A19: New | B19: =COUNTIF(Clean_Data!$M:$M,A19) -> 191 | C19: =SUMIFS(Clean_Data!$I:$I,Clean_Data!$M:$M,A19,Clean_Data!$L:$L,"Completed") -> 9056.14
A20: Returning | B20: =COUNTIF(Clean_Data!$M:$M,A20) -> 162 | C20: =SUMIFS(Clean_Data!$I:$I,Clean_Data!$M:$M,A20,Clean_Data!$L:$L,"Completed") -> 6517.74
A21: Wholesale | B21: =COUNTIF(Clean_Data!$M:$M,A21) -> 146 | C21: =SUMIFS(Clean_Data!$I:$I,Clean_Data!$M:$M,A21,Clean_Data!$L:$L,"Completed") -> 7898.26
A22: Unknown | B22: =COUNTIF(Clean_Data!$M:$M,A22) -> 1 | C22: =SUMIFS(Clean_Data!$I:$I,Clean_Data!$M:$M,A22,Clean_Data!$L:$L,"Completed") -> 24.06

Sheet Advanced_Formulas
B1: Advanced Formulas — Demonstration & Results
A3: Formula Skill | B3: Input / Key | C3: Result | D3: Formula Used | F3: Interactive Formula Inputs
A4: XLOOKUP / VLOOKUP | B4: 99999 | C4: =IFERROR(_xlfn.XLOOKUP(B4,Clean_Data!$B:$B,Clean_Data!$C:$C),"Not Found") -> Not Found | D4: =IFERROR(_xlfn.XLOOKUP(B4,Clean_Data!$B:$B,Clean_Data!$C:$C),"Not Found") -> Not Found | F4: Selected Country | G4: All
A5: INDEX-MATCH | B5: Germany | C5: =INDEX(Pivot_Summary!$D$5:$D$14,MATCH(B5,Pivot_Summary!$A$5:$A$14,0)) -> 2467.38 | D5: =INDEX([1]Pivot_Summary!$D$5:$D$14,MATCH(B5,[1]Pivot_Summary!$A$5:$A$14,0)) -> 2467.38 | F5: Selected Year | G5: 2024
A6: IF condition | B6: 100 | C6: =IF(B6>=100,"High","Low") -> High | D6: =IF(B6>=100,"High","Low") -> High | F6: Filtered Revenue | G6: =IF(G4="All",SUMIFS(Clean_Data!$I:$I,Clean_Data!$K:$K,G5,Clean_Data!$L:$L,"Completed"),SUMIFS(Clean_Data!$I:$I,Clean_Data!$H:$H,G4,Clean_Data!$K:$K,G5,Clean_Data!$L:$L,"Completed")) -> 23496.2
A7: Nested IF | B7: 2500 | C7: =IF(B7>=5000,"Platinum",IF(B7>=2500,"Gold",IF(B7>=1000,"Silver","Bronze"))) -> Gold | D7: =IF(B7>=5000,"Platinum",IF(B7>=2500,"Gold",IF(B7>=1000,"Silver","Bronze"))) -> Gold
A8: SUMIFS | B8: United Kingdom | C8: =SUMIFS(Clean_Data!$I:$I,Clean_Data!$H:$H,B8,Clean_Data!$L:$L,"Completed") -> 1695.54 | D8: =SUMIFS(Clean_Data!$I:$I,Clean_Data!$H:$H,B8,Clean_Data!$L:$L,"Completed") -> 1695.54
A9: COUNTIFS | B9: Completed | C9: =COUNTIFS(Clean_Data!$L:$L,B9) -> 461 | D9: =COUNTIFS(Clean_Data!$L:$L,B9) -> 461
A13: Country | B13: Revenue | C13: Rank | D13: Performance
A14: United Kingdom | B14: =SUMIFS(Clean_Data!$I:$I,Clean_Data!$H:$H,A14,Clean_Data!$L:$L,"Completed") -> 1695.54 | C14: =RANK(B14,$B$14:$B$23,0) -> 9 | D14: =IF(B14>=LARGE($B$14:$B$23,3),"Top 3",IF(B14>=AVERAGE($B$14:$B$23),"Above Average","Below Average")) -> Below Average
A15: Germany | B15: =SUMIFS(Clean_Data!$I:$I,Clean_Data!$H:$H,A15,Clean_Data!$L:$L,"Completed") -> 2467.38 | C15: =RANK(B15,$B$14:$B$23,0) -> 4 | D15: =IF(B15>=LARGE($B$14:$B$23,3),"Top 3",IF(B15>=AVERAGE($B$14:$B$23),"Above Average","Below Average")) -> Above Average
A16: France | B16: =SUMIFS(Clean_Data!$I:$I,Clean_Data!$H:$H,A16,Clean_Data!$L:$L,"Completed") -> 2071.56 | C16: =RANK(B16,$B$14:$B$23,0) -> 7 | D16: =IF(B16>=LARGE($B$14:$B$23,3),"Top 3",IF(B16>=AVERAGE($B$14:$B$23),"Above Average","Below Average")) -> Below Average
A17: EIRE | B17: =SUMIFS(Clean_Data!$I:$I,Clean_Data!$H:$H,A17,Clean_Data!$L:$L,"Completed") -> 1997.95 | C17: =RANK(B17,$B$14:$B$23,0) -> 8 | D17: =IF(B17>=LARGE($B$14:$B$23,3),"Top 3",IF(B17>=AVERAGE($B$14:$B$23),"Above Average","Below Average")) -> Below Average
A18: Spain | B18: =SUMIFS(Clean_Data!$I:$I,Clean_Data!$H:$H,A18,Clean_Data!$L:$L,"Completed") -> 1398.13 | C18: =RANK(B18,$B$14:$B$23,0) -> 10 | D18: =IF(B18>=LARGE($B$14:$B$23,3),"Top 3",IF(B18>=AVERAGE($B$14:$B$23),"Above Average","Below Average")) -> Below Average
A19: Netherlands | B19: =SUMIFS(Clean_Data!$I:$I,Clean_Data!$H:$H,A19,Clean_Data!$L:$L,"Completed") -> 3449.53 | C19: =RANK(B19,$B$14:$B$23,0) -> 1 | D19: =IF(B19>=LARGE($B$14:$B$23,3),"Top 3",IF(B19>=AVERAGE($B$14:$B$23),"Above Average","Below Average")) -> Top 3
A20: Belgium | B20: =SUMIFS(Clean_Data!$I:$I,Clean_Data!$H:$H,A20,Clean_Data!$L:$L,"Completed") -> 2390.51 | C20: =RANK(B20,$B$14:$B$23,0) -> 5 | D20: =IF(B20>=LARGE($B$14:$B$23,3),"Top 3",IF(B20>=AVERAGE($B$14:$B$23),"Above Average","Below Average")) -> Above Average
A21: Switzerland | B21: =SUMIFS(Clean_Data!$I:$I,Clean_Data!$H:$H,A21,Clean_Data!$L:$L,"Completed") -> 2594.1 | C21: =RANK(B21,$B$14:$B$23,0) -> 3 | D21: =IF(B21>=LARGE($B$14:$B$23,3),"Top 3",IF(B21>=AVERAGE($B$14:$B$23),"Above Average","Below Average")) -> Top 3
A22: Portugal | B22: =SUMIFS(Clean_Data!$I:$I,Clean_Data!$H:$H,A22,Clean_Data!$L:$L,"Completed") -> 3175.02 | C22: =RANK(B22,$B$14:$B$23,0) -> 2 | D22: =IF(B22>=LARGE($B$14:$B$23,3),"Top 3",IF(B22>=AVERAGE($B$14:$B$23),"Above Average","Below Average")) -> Top 3
A23: Australia | B23: =SUMIFS(Clean_Data!$I:$I,Clean_Data!$H:$H,A23,Clean_Data!$L:$L,"Completed") -> 2256.48 | C23: =RANK(B23,$B$14:$B$23,0) -> 6 | D23: =IF(B23>=LARGE($B$14:$B$23,3),"Top 3",IF(B23>=AVERAGE($B$14:$B$23),"Above Average","Below Average")) -> Below Average

Sheet pivot_table
A2: Row Labels | B2: Count of OrderStatus | D2: Row Labels | E2: Sum of Revenue | G2: Row Labels | H2: Count of OrderStatus
A3: Australia | B3: 51 | D3: Jan | E3: 1924.1 | G3: Jan | H3: 42
A4: Belgium | B4: 52 | D4: Feb | E4: 1660.02 | G4: Feb | H4: 46
A5: EIRE | B5: 47 | D5: Mar | E5: 1304.35 | G5: Mar | H5: 40
A6: France | B6: 51 | D6: Apr | E6: 1051.24 | G6: Apr | H6: 32
A7: Germany | B7: 53 | D7: May | E7: 1488.53 | G7: May | H7: 38
A8: Netherlands | B8: 59 | D8: Jun | E8: 2108.07 | G8: Jun | H8: 44
A9: Portugal | B9: 54 | D9: Jul | E9: 2324.74 | G9: Jul | H9: 49
A10: Spain | B10: 45 | D10: Aug | E10: 3590.75 | G10: Aug | H10: 49
A11: Switzerland | B11: 49 | D11: Sep | E11: 2061.74 | G11: Sep | H11: 41
A12: United Kingdom | B12: 39 | D12: Oct | E12: 2046.69 | G12: Oct | H12: 40
A13: Grand Total | B13: 500 | D13: Nov | E13: 1495.62 | G13: Nov | H13: 38
D14: Dec | E14: 2017.5 | G14: Dec | H14: 41
D15: Grand Total | E15: 23073.35 | G15: Grand Total | H15: 500

Sheet Documentation
A1: Documentation & Submission Guide
A3: 1. Dataset Source | B3: UCI Machine Learning Repository — Online Retail. The original dataset contains UK online-retail transactions and the fields used here include invoice, stock code, description, quantity, date, unit price, customer and country.
A4: 2. Raw Data | B4: Raw_Data contains the imported/project dataset before preparation. A small number of blanks and a duplicate are intentionally present to demonstrate cleaning.
A5: 3. Cleaning | B5: Clean_Data removes the duplicate, replaces missing quantity/customer values, standardizes cancellation status, and creates Revenue, Month, Year and CustomerSegment fields.
A6: 4. Pivot Analysis | B6: Pivot_Summary contains formula-based pivot-style summaries for country, month and customer segment. These are designed to be easy to inspect and refresh in Excel.
A7: 5. Advanced Formulas | B7: Advanced_Formulas demonstrates XLOOKUP, INDEX-MATCH, IF, nested IF, SUMIFS, COUNTIFS, RANK and AVERAGE.
A8: 6. Dashboard | B8: Dashboard provides KPI cards, a country selector, year selector, monthly trend, product comparison and country revenue chart.
A9: 7. Interactivity | B9: Use the Country dropdown on Dashboard to change the KPI and chart calculations. The project uses dropdown controls as a lightweight alternative to native Excel slicers.
A10: 8. Presentation | B10: Keep Dashboard as the first working sheet during submission, check formulas, verify charts, and save the final workbook using YourName_ExcelDashboard.xlsx.
A11: 9. 50-Mark Mapping | B11: Dataset 2.5 | Cleaning 5 | Pivot/Summary 7.5 | Advanced Formulas 7.5 | Visualization 10 | Interactive Dashboard 12.5 | Documentation 5 = 50 marks.
